{
	"region_name": "REGION V",
	"province_list": {
		"ALBAY": {
			"municipality_list": {
				"BACACAY": {
					"barangay_list": [
						"BACLAYON",
						"BANAO",
						"BARANGAY 1 (POB.)",
						"BARANGAY 2 (POB.)",
						"BARANGAY 3 (POB.)",
						"BARANGAY 4 (POB.)",
						"BARANGAY 5 (POB.)",
						"BARANGAY 6 (POB.)",
						"BARANGAY 7 (POB.)",
						"BARANGAY 8 (POB.)",
						"BARANGAY 9 (POB.)",
						"BARANGAY 10 (POB.)",
						"BARANGAY 11 (POB.)",
						"BARANGAY 12 (POB.)",
						"BARANGAY 13 (POB.)",
						"BARANGAY 14 (POB.)",
						"BARIW",
						"BASUD",
						"BAYANDONG",
						"BONGA (UPPER)",
						"BUANG",
						"BUSDAC (SAN JOSE)",
						"CABASAN",
						"CAGBULACAO",
						"CAGRARAY",
						"CAJOGUTAN",
						"CAWAYAN",
						"DAMACAN",
						"GUBAT ILAWOD",
						"GUBAT IRAYA",
						"HINDI",
						"IGANG",
						"LANGATON",
						"MANAET",
						"MAPULANG DAGA",
						"MATAAS",
						"MISIBIS",
						"NAHAPUNAN",
						"NAMANDAY",
						"NAMANTAO",
						"NAPAO",
						"PANARAYON",
						"PIGCOBOHAN",
						"PILI ILAWOD",
						"PILI IRAYA",
						"PONGCO (LOWER BONGA)",
						"SAN PABLO",
						"SAN PEDRO",
						"SOGOD",
						"SULA",
						"TAMBILAGAO (TAMBOGNON)",
						"TAMBONGON (TAMBILAGAO)",
						"TANAGAN",
						"USON",
						"VINISITAHAN-BASUD (MAINLAND)",
						"VINISITAHAN-NAPAO (ISLAND)"
					]
				},
				"CAMALIG": {
					"barangay_list": [
						"ANOLING",
						"BALIGANG",
						"BANTONAN",
						"BARANGAY 1 (POB.)",
						"BARANGAY 2 (POB.)",
						"BARANGAY 3 (POB.)",
						"BARANGAY 4 (POB.)",
						"BARANGAY 5 (POB.)",
						"BARANGAY 6 (POB.)",
						"BARANGAY 7 (POB.)",
						"BARIW",
						"BINANDERAHAN",
						"BINITAYAN",
						"BONGABONG",
						"CABAGÑAN",
						"CABRARAN PEQUEÑO",
						"CAGUIBA",
						"CALABIDONGAN",
						"COMUN",
						"COTMON",
						"DEL ROSARIO",
						"GAPO",
						"GOTOB",
						"ILAWOD",
						"ILULUAN",
						"LIBOD",
						"LIGBAN",
						"MABUNGA",
						"MAGOGON",
						"MANAWAN",
						"MANINILA",
						"MINA",
						"MITI",
						"PALANOG",
						"PANOYPOY",
						"PARIAAN",
						"QUINARTILAN",
						"QUIRANGAY",
						"QUITINDAY",
						"SALUGAN",
						"SOLONG",
						"SUA",
						"SUMLANG",
						"TAGAYTAY",
						"TAGOYTOY",
						"TALADONG",
						"TALOTO",
						"TAPLACON",
						"TINAGO",
						"TUMPA"
					]
				},
				"CITY OF LIGAO": {
					"barangay_list": [
						"ABELLA",
						"ALLANG",
						"AMTIC",
						"BACONG",
						"BAGUMBAYAN",
						"BALANAC",
						"BALIGANG",
						"BARAYONG",
						"BASAG",
						"BATANG",
						"BAY",
						"BINANOWAN",
						"BINATAGAN (POB.)",
						"BOBONSURAN",
						"BONGA",
						"BUSAC",
						"BUSAY",
						"CABARIAN",
						"CALZADA (POB.)",
						"CATBURAWAN",
						"CAVASI",
						"CULLIAT",
						"DUNAO",
						"FRANCIA",
						"GUILID",
						"HERRERA",
						"LAYON",
						"MACALIDONG",
						"MAHABA",
						"MALAMA",
						"MAONON",
						"NABONTON",
						"NASISI",
						"OMA-OMA",
						"PALAPAS",
						"PANDAN",
						"PAULBA",
						"PAULOG",
						"PINAMANIQUIAN",
						"PINIT",
						"RANAO-RANAO",
						"SAN VICENTE",
						"SANTA CRUZ (POB.)",
						"TAGPO",
						"TAMBO",
						"TANDARURA",
						"TASTAS",
						"TINAGO",
						"TINAMPO",
						"TIONGSON",
						"TOMOLIN",
						"TUBURAN",
						"TULA-TULA GRANDE",
						"TULA-TULA PEQUEÑO",
						"TUPAS"
					]
				},
				"DARAGA (LOCSIN)": {
					"barangay_list": [
						"ALCALA",
						"ALOBO",
						"ANISLAG",
						"BAGUMBAYAN",
						"BALINAD",
						"BAÑADERO",
						"BAÑAG",
						"BASCARAN",
						"BIGAO",
						"BINITAYAN",
						"BONGALON",
						"BUDIAO",
						"BURGOS",
						"BUSAY",
						"CANAROM",
						"CULLAT",
						"DELA PAZ",
						"DINORONAN",
						"GABAWAN",
						"GAPO",
						"IBAUGAN",
						"ILAWOD AREA POB. (DIST. 2)",
						"INARADO",
						"KIDACO",
						"KILICAO",
						"KIMANTONG",
						"KINAWITAN",
						"KIWALO",
						"LACAG",
						"MABINI",
						"MALABOG",
						"MALOBAGO",
						"MAOPI",
						"MARKET AREA POB. (DIST. 1)",
						"MAROROY",
						"MATNOG",
						"MAYON",
						"MI-ISI",
						"NABASAN",
						"NAMANTAO",
						"PANDAN",
						"PEÑAFRANCIA",
						"SAGPON",
						"SALVACION",
						"SAN RAFAEL",
						"SAN RAMON",
						"SAN ROQUE",
						"SAN VICENTE GRANDE",
						"SAN VICENTE PEQUEÑO",
						"SIPI",
						"TABON-TABON",
						"TAGAS",
						"TALAHIB",
						"VILLAHERMOSA"
					]
				},
				"GUINOBATAN": {
					"barangay_list": [
						"AGPAY",
						"BALITE",
						"BANAO",
						"BATBAT",
						"BINOGSACAN LOWER",
						"BINOGSACAN UPPER",
						"BOLOLO",
						"BUBULUSAN",
						"CALZADA",
						"CATOMAG",
						"DOÑA MERCEDES",
						"DOÑA TOMASA (MAGATOL)",
						"ILAWOD",
						"INAMNAN GRANDE",
						"INAMNAN PEQUEÑO",
						"INASCAN",
						"IRAYA",
						"LOMACAO",
						"MAGUIRON",
						"MAIPON",
						"MALABNIG",
						"MALIPO",
						"MALOBAGO",
						"MANINILA",
						"MAPACO",
						"MARCIAL O. RAÑOLA (CABALOAON)",
						"MASARAWAG",
						"MAURARO",
						"MINTO",
						"MORERA",
						"MULADBUCAD GRANDE",
						"MULADBUCAD PEQUEÑO",
						"ONGO",
						"PALANAS",
						"POBLACION",
						"POOD",
						"QUIBONGBONGAN",
						"QUITAGO",
						"SAN FRANCISCO",
						"SAN JOSE (OGSONG)",
						"SAN RAFAEL",
						"SINUNGTAN",
						"TANDARORA",
						"TRAVESIA"
					]
				},
				"JOVELLAR": {
					"barangay_list": [
						"AURORA POB. (BGY. 6)",
						"BAGACAY",
						"BAUTISTA",
						"CABRARAN",
						"CALZADA POB. (BGY. 7)",
						"DEL ROSARIO",
						"ESTRELLA",
						"FLORISTA",
						"MABINI POB. (BGY. 2)",
						"MAGSAYSAY POB (BGY. 4)",
						"MAMLAD",
						"MAOGOG",
						"MERCADO POB. (BGY. 5)",
						"PLAZA POB. (BGY. 3)",
						"QUITINDAY POB. (BGY. 8)",
						"RIZAL POB. (BGY. 1)",
						"SALVACION",
						"SAN ISIDRO",
						"SAN ROQUE",
						"SAN VICENTE",
						"SINAGARAN",
						"VILLA PAZ",
						"WHITE DEER POB. (BGY. 9)"
					]
				},
				"LEGAZPI CITY": {
					"barangay_list": [
						"BGY. 1 - EM'S BARRIO (POB.)",
						"BGY. 2 - EM'S BARRIO SOUTH (POB.)",
						"BGY. 3 - EM'S BARRIO EAST (POB.)",
						"BGY. 4 - SAGPON POB. (SAGPON 1)",
						"BGY. 5 - SAGMIN POB. (SAGPON 2)",
						"BGY. 6 - BAÑADERO POB. (SAGPON 3)",
						"BGY. 7 - BAÑO (POB.)",
						"BGY. 8 - BAGUMBAYAN (POB.)",
						"BGY. 9 - PINARIC (POB.)",
						"BGY. 10 - CABUGAO",
						"BGY. 11 - MAOYOD POB. (BGY. 10 AND 11)",
						"BGY. 12 - TULA-TULA (POB.)",
						"BGY. 13 - ILAWOD WEST POB. (ILAWOD 1)",
						"BGY. 14 - ILAWOD POB. (ILAWOD 2)",
						"BGY. 15 - ILAWOD EAST POB. (ILAWOD 3)",
						"BGY. 16 - KAWIT-EAST WASHINGTON DRIVE (POB.)",
						"BGY. 17 - RIZAL SREET., ILAWOD (POB.)",
						"BGY. 18 - CABAGÑAN WEST (POB.)",
						"BGY. 19 - CABAGÑAN",
						"BGY. 20 - CABAGÑAN EAST (POB.)",
						"BGY. 21 - BINANUAHAN WEST (POB.)",
						"BGY. 22 - BINANUAHAN EAST (POB.)",
						"BGY. 23 - IMPERIAL COURT SUBD. (POB.)",
						"BGY. 24 - RIZAL STREET",
						"BGY. 25 - LAPU-LAPU (POB.)",
						"BGY. 26 - DINAGAAN (POB.)",
						"BGY. 27 - VICTORY VILLAGE SOUTH (POB.)",
						"BGY. 28 - VICTORY VILLAGE NORTH (POB.)",
						"BGY. 29 - SABANG (POB.)",
						"BGY. 30 - PIGCALE (POB.)",
						"BGY. 31 - CENTRO-BAYBAY (POB.)",
						"BGY. 32 - SAN ROQUE (BGY. 66)",
						"BGY. 33 - PNR-PEÑARANDA ST.-IRAYA (POB.)",
						"BGY. 34 - ORO SITE-MAGALLANES ST. (POB.)",
						"BGY. 35 - TINAGO (POB.)",
						"BGY. 36 - KAPANTAWAN (POB.)",
						"BGY. 37 - BITANO (POB.)",
						"BGY. 38 - GOGON (BGY. 54)",
						"BGY. 39 - BONOT (POB.)",
						"BGY. 40 - CRUZADA (BGY. 52)",
						"BGY. 41 - BOGTONG (BGY. 45)",
						"BGY. 42 - RAWIS (BGY. 65)",
						"BGY. 43 - TAMAOYAN (BGY. 67)",
						"BGY. 44 - PAWA (BGY. 61)",
						"BGY. 45 - DITA (BGY. 51)",
						"BGY. 46 - SAN JOAQUIN (BGY. 64)",
						"BGY. 47 - ARIMBAY",
						"BGY. 48 - BAGONG ABRE (BGY. 42)",
						"BGY. 49 - BIGAA (BGY. 44)",
						"BGY. 50 - PADANG (BGY. 60)",
						"BGY. 51 - BUYUAN (BGY. 49)",
						"BGY. 52 - MATANAG",
						"BGY. 53 - BONGA (BGY. 48)",
						"BGY. 54 - MABINIT (BGY. 59)",
						"BGY. 55 - ESTANZA (BGY. 53)",
						"BGY. 56 - TAYSAN (BGY. 68)",
						"BGY. 57 - DAP-DAP (BGY. 69)",
						"BGY. 58 - BURAGWIS",
						"BGY. 59 - PURO (BGY. 63)",
						"BGY. 60 - LAMBA",
						"BGY. 61 - MASLOG (BGY. 58)",
						"BGY. 62 - HOMAPON (BGY. 55)",
						"BGY. 63 - MARIAWA (BGY. 56)",
						"BGY. 64 - BAGACAY (BGY. 41 BAGACAY)",
						"BGY. 65 - IMALNOD (BGY. 57)",
						"BGY. 66 - BANQUEROHAN (BGY. 43)",
						"BGY. 67 - BARIIS (BGY. 46)",
						"BGY. 68 - SAN FRANCISCO (BGY. 62)",
						"BGY. 69 - BUENAVISTA (BGY.47)",
						"BGY. 70 - CAGBACONG (BGY. 50)"
					]
				},
				"LIBON": {
					"barangay_list": [
						"ALONGONG",
						"APUD",
						"BACOLOD",
						"BARIW",
						"BONBON",
						"BUGA",
						"BULUSAN",
						"BURABOD",
						"CAGUSCOS",
						"EAST CARISAC",
						"HARIGUE",
						"LIBTONG",
						"LINAO",
						"MABAYAWAS",
						"MACABUGOS",
						"MAGALLANG",
						"MALABIGA",
						"MARAYAG",
						"MATARA",
						"MOLOSBOLOS",
						"NATASAN",
						"NIÑO JESUS (SANTO NIÑO JESUS)",
						"NOGPO",
						"PANTAO",
						"RAWIS",
						"SAGRADA FAMILIA",
						"SALVACION",
						"SAMPONGAN",
						"SAN AGUSTIN",
						"SAN ANTONIO",
						"SAN ISIDRO",
						"SAN JOSE",
						"SAN PASCUAL",
						"SAN RAMON",
						"SAN VICENTE",
						"SANTA CRUZ",
						"TALIN-TALIN",
						"TAMBO",
						"VILLA PETRONA",
						"WEST CARISAC",
						"ZONE I (POB.)",
						"ZONE II (POB.)",
						"ZONE III (POB.)",
						"ZONE IV (POB.)",
						"ZONE V (POB.)",
						"ZONE VI (POB.)",
						"ZONE VII (POB.)"
					]
				},
				"MALILIPOT": {
					"barangay_list": [
						"BARANGAY I (POB.)",
						"BARANGAY II (POB.)",
						"BARANGAY III (POB.)",
						"BARANGAY IV (POB.)",
						"BARANGAY V (POB.)",
						"BINITAYAN",
						"CALBAYOG",
						"CANAWAY",
						"SALVACION",
						"SAN ANTONIO SANTICON (POB.)",
						"SAN ANTONIO SULONG",
						"SAN FRANCISCO",
						"SAN ISIDRO ILAWOD",
						"SAN ISIDRO IRAYA",
						"SAN JOSE",
						"SAN ROQUE",
						"SANTA CRUZ",
						"SANTA TERESA"
					]
				},
				"MALINAO": {
					"barangay_list": [
						"AWANG",
						"BAGATANGKI",
						"BAGUMBAYAN",
						"BALADING",
						"BALZA",
						"BARIW",
						"BAYBAY",
						"BULANG",
						"BURABOD",
						"CABUNTURAN",
						"COMUN",
						"DIARO",
						"ESTANCIA",
						"JONOP",
						"LABNIG",
						"LIBOD",
						"MALOLOS",
						"MATALIPNI",
						"OGOB",
						"PAWA",
						"PAYAHAN",
						"POBLACION",
						"QUINARABASAHAN",
						"SANTA ELENA",
						"SOA",
						"SUGCAD",
						"TAGOYTOY",
						"TANAWAN",
						"TULIW"
					]
				},
				"MANITO": {
					"barangay_list": [
						"BALABAGON",
						"BALASBAS",
						"BAMBAN",
						"BUYO",
						"CABACONGAN",
						"CABIT",
						"CAWAYAN",
						"CAWIT",
						"HOLUGAN",
						"IT-BA (POB.)",
						"MALOBAGO",
						"MANUMBALAY",
						"NAGOTGOT",
						"PAWA",
						"TINAPIAN"
					]
				},
				"OAS": {
					"barangay_list": [
						"BADBAD",
						"BADIAN",
						"BAGSA",
						"BAGUMBAYAN",
						"BALOGO",
						"BANAO",
						"BANGIAWON",
						"BOGTONG",
						"BONGORAN",
						"BUSAC",
						"CADAWAG",
						"CAGMANABA",
						"CALAGUIMIT",
						"CALPI",
						"CALZADA",
						"CAMAGONG",
						"CASINAGAN",
						"CENTRO POBLACION",
						"COLIAT",
						"DEL ROSARIO",
						"GUMABAO",
						"ILAOR NORTE",
						"ILAOR SUR",
						"IRAYA NORTE",
						"IRAYA SUR",
						"MANGA",
						"MAPORONG",
						"MARAMBA",
						"MATAMBO",
						"MAYAG",
						"MAYAO",
						"MOROPONROS",
						"NAGAS",
						"OBALIW-RINAS",
						"PISTOLA",
						"RAMAY",
						"RIZAL",
						"SABAN",
						"SAN AGUSTIN",
						"SAN ANTONIO",
						"SAN ISIDRO",
						"SAN JOSE",
						"SAN JUAN",
						"SAN MIGUEL",
						"SAN PASCUAL (NALE)",
						"SAN RAMON",
						"SAN VICENTE (SUCA)",
						"TABLON",
						"TALISAY",
						"TALONGOG",
						"TAPEL",
						"TOBGON",
						"TOBOG"
					]
				},
				"PIO DURAN": {
					"barangay_list": [
						"AGOL",
						"ALABANGPURO",
						"BANAWAN (BINAWAN)",
						"BARANGAY I (POB.)",
						"BARANGAY II (POB.)",
						"BARANGAY III (POB.)",
						"BARANGAY IV (POB.)",
						"BARANGAY V (POB.)",
						"BASICAO COASTAL",
						"BASICAO INTERIOR",
						"BINODEGAHAN",
						"BUENAVISTA",
						"BUYO",
						"CARATAGAN",
						"CUYAOYAO",
						"FLORES",
						"LA MEDALLA",
						"LAWINON",
						"MACASITAS",
						"MALAPAY",
						"MALIDONG",
						"MAMLAD",
						"MARIGONDON",
						"MATANGLAD",
						"NABLANGBULOD",
						"ORINGON",
						"PALAPAS",
						"PANGANIRAN",
						"RAWIS",
						"SALVACION",
						"SANTO CRISTO",
						"SUKIP",
						"TIBABO"
					]
				},
				"POLANGUI": {
					"barangay_list": [
						"AGOS",
						"ALNAY",
						"ALOMON",
						"AMOGUIS",
						"ANOPOL",
						"APAD",
						"BALABA",
						"BALANGIBANG",
						"BALINAD",
						"BASUD",
						"BINAGBANGAN (PINTOR)",
						"BUYO",
						"CENTRO OCCIDENTAL (POB.)",
						"CENTRO ORIENTAL (POB.)",
						"CEPRES",
						"COTMON",
						"COTNOGAN",
						"DANAO",
						"GABON",
						"GAMOT",
						"ITARAN",
						"KINALE",
						"KINUARTILAN",
						"LA MEDALLA",
						"LA PURISIMA",
						"LANIGAY",
						"LIDONG",
						"LOURDES",
						"MAGPANAMBO",
						"MAGURANG",
						"MATACON",
						"MAYNAGA",
						"MAYSUA",
						"MENDEZ",
						"NAPO",
						"PINAGDAPUGAN",
						"PONSO",
						"SALVACION",
						"SAN ROQUE",
						"SANTA CRUZ",
						"SANTA TERESITA",
						"SANTICON",
						"SUGCAD",
						"UBALIW"
					]
				},
				"RAPU-RAPU": {
					"barangay_list": [
						"BAGAOBAWAN",
						"BATAN",
						"BILBAO",
						"BINOSAWAN",
						"BOGTONG",
						"BUENAVISTA",
						"BUHATAN",
						"CALANAGA",
						"CARACARAN",
						"CAROGCOG",
						"DAP-DAP",
						"GABA",
						"GALICIA",
						"GUADALUPE",
						"HAMORAWON",
						"LAGUNDI",
						"LIGUAN",
						"LINAO",
						"MALOBAGO",
						"MANANAO",
						"MANCAO",
						"MANILA",
						"MASAGA",
						"MOROCBOROCAN",
						"NAGCALSOT",
						"PAGCOLBON",
						"POBLACION",
						"SAGRADA",
						"SAN RAMON",
						"SANTA BARBARA",
						"TINOCAWAN",
						"TINOPAN",
						"VIGA",
						"VILLAHERMOSA"
					]
				},
				"SANTO DOMINGO (LIBOG)": {
					"barangay_list": [
						"ALIMSOG",
						"BAGONG SAN ROQUE",
						"BUHATAN",
						"CALAYUCAY",
						"DEL ROSARIO POB. (BGY. 3)",
						"FIDEL SURTIDA",
						"LIDONG",
						"MARKET SITE POB. (BGY. 9)",
						"NAGSIYA POB. (BGY. 8)",
						"PANDAYAN POB. (BGY. 10)",
						"SALVACION",
						"SAN ANDRES",
						"SAN FERNANDO",
						"SAN FRANCISCO POB. (BGY. 1)",
						"SAN ISIDRO",
						"SAN JUAN POB. (BGY. 2)",
						"SAN PEDRO POB. (BGY. 5)",
						"SAN RAFAEL POB. (BGY. 7)",
						"SAN ROQUE",
						"SAN VICENTE POB. (BGY. 6.)",
						"SANTA MISERICORDIA",
						"SANTO DOMINGO POB. (BGY. 4)",
						"SANTO NIÑO"
					]
				},
				"TABACO CITY": {
					"barangay_list": [
						"AGNAS (SAN MIGUEL ISLAND)",
						"BACOLOD",
						"BANGKILINGAN",
						"BANTAYAN",
						"BARANGHAWON",
						"BASAGAN",
						"BASUD (POB.)",
						"BOGÑABONG",
						"BOMBON (POB.)",
						"BONOT",
						"BUANG",
						"BUHIAN",
						"CABAGÑAN",
						"COBO",
						"COMON",
						"CORMIDAL",
						"DIVINO ROSTRO (POB.)",
						"FATIMA",
						"GUINOBAT",
						"HACIENDA (SAN MIGUEL ISLAND)",
						"MAGAPO",
						"MARIROC",
						"MATAGBAC",
						"ORAS",
						"OSON",
						"PANAL",
						"PAWA",
						"PINAGBOBONG",
						"QUINALE CABASAN (POB.)",
						"QUINASTILLOJAN",
						"RAWIS (SAN MIGUEL ISLAND)",
						"SAGURONG (SAN MIGUEL ISLAND)",
						"SALVACION",
						"SAN ANTONIO",
						"SAN CARLOS",
						"SAN ISIDRO (BORING)",
						"SAN JUAN (POB.)",
						"SAN LORENZO",
						"SAN RAMON",
						"SAN ROQUE",
						"SAN VICENTE",
						"SANTO CRISTO (POB.)",
						"SUA-IGOT",
						"TABIGUIAN",
						"TAGAS",
						"TAYHI (POB.)",
						"VISITA (SAN MIGUEL ISLAND)"
					]
				},
				"TIWI": {
					"barangay_list": [
						"BAGUMBAYAN",
						"BARIIS",
						"BAYBAY",
						"BELEN (MALABOG)",
						"BIYONG",
						"BOLO",
						"CALE",
						"CARARAYAN",
						"CORO-CORO",
						"DAP-DAP",
						"GAJO",
						"JOROAN",
						"LIBJO",
						"LIBTONG",
						"MATALIBONG",
						"MAYNONONG",
						"MAYONG",
						"MISIBIS",
						"NAGA",
						"NAGAS",
						"OYAMA",
						"PUTSAN",
						"SAN BERNARDO",
						"SOGOD",
						"TIGBI (POB.)"
					]
				}
			}
		},
		"CAMARINES NORTE": {
			"municipality_list": {
				"BASUD": {
					"barangay_list": [
						"ANGAS",
						"BACTAS",
						"BINATAGAN",
						"CAAYUNAN",
						"GUINATUNGAN",
						"HINAMPACAN",
						"LANGA",
						"LANITON",
						"LIDONG",
						"MAMPILI",
						"MANDAZO",
						"MANGCAMAGONG",
						"MANMUNTAY",
						"MANTUGAWE",
						"MATNOG",
						"MOCONG",
						"OLIVA",
						"PAGSANGAHAN",
						"PINAGWARASAN",
						"PLARIDEL",
						"POBLACION 1",
						"POBLACION 2",
						"SAN FELIPE",
						"SAN JOSE",
						"SAN PASCUAL",
						"TABA-TABA",
						"TACAD",
						"TAISAN",
						"TUACA"
					]
				},
				"CAPALONGA": {
					"barangay_list": [
						"ALAYAO",
						"BINAWANGAN",
						"CALABACA",
						"CAMAGSAAN",
						"CATABAGUANGAN",
						"CATIOAN",
						"DEL PILAR",
						"ITOK",
						"LUCBANAN",
						"MABINI",
						"MACTANG",
						"MAGSAYSAY",
						"MATAQUE",
						"OLD CAMP",
						"POBLACION",
						"SAN ANTONIO",
						"SAN ISIDRO",
						"SAN ROQUE",
						"TANAWAN",
						"UBANG",
						"VILLA AURORA",
						"VILLA BELEN"
					]
				},
				"DAET": {
					"barangay_list": [
						"ALAWIHAO",
						"AWITAN",
						"BAGASBAS",
						"BARANGAY I (POB.)",
						"BARANGAY II (POB.)",
						"BARANGAY III (POB.)",
						"BARANGAY IV (POB.)",
						"BARANGAY V (POB.)",
						"BARANGAY VI (POB.)",
						"BARANGAY VII (POB.)",
						"BARANGAY VIII (POB.)",
						"BIBIRAO",
						"BORABOD",
						"CALASGASAN",
						"CAMAMBUGAN",
						"COBANGBANG (CARUMPIT)",
						"DOGONGAN",
						"GAHONON",
						"GUBAT",
						"LAG-ON",
						"MAGANG",
						"MAMBALITE",
						"MANCRUZ (MANGCRUZ)",
						"PAMORANGON",
						"SAN ISIDRO"
					]
				},
				"JOSE PANGANIBAN": {
					"barangay_list": [
						"BAGONG BAYAN",
						"CALERO",
						"DAHICAN",
						"DAYHAGAN",
						"LARAP",
						"LUKLUKAN NORTE",
						"LUKLUKAN SUR",
						"MOTHERLODE",
						"NAKALAYA",
						"NORTH POBLACION",
						"OSMEÑA",
						"PAG-ASA",
						"PARANG",
						"PLARIDEL",
						"SALVACION",
						"SAN ISIDRO",
						"SAN JOSE",
						"SAN MARTIN",
						"SAN PEDRO",
						"SAN RAFAEL",
						"SANTA CRUZ",
						"SANTA ELENA",
						"SANTA MILAGROSA",
						"SANTA ROSA NORTE",
						"SANTA ROSA SUR",
						"SOUTH POBLACION",
						"TAMISAN"
					]
				},
				"LABO": {
					"barangay_list": [
						"ANAHAW (POB.)",
						"ANAMEAM",
						"AWITAN",
						"BAAY",
						"BAGACAY",
						"BAGONG SILANG I",
						"BAGONG SILANG II",
						"BAGONG SILANG III (SILANG)",
						"BAKIAD",
						"BAUTISTA",
						"BAYABAS",
						"BAYAN-BAYAN",
						"BENIT",
						"BULHAO",
						"CABATUHAN",
						"CABUSAY",
						"CALABASA",
						"CANAPAWAN",
						"DAGUIT",
						"DALAS",
						"DUMAGMANG",
						"EXCIBAN",
						"FUNDADO",
						"GUINACUTAN",
						"GUISICAN",
						"GUMAMELA (POB.)",
						"IBERICA",
						"KALAMUNDING (POB.)",
						"LUGUI",
						"MABILO I",
						"MABILO II",
						"MACOGON",
						"MAHAWAN-HAWAN",
						"MALANGCAO-BASUD",
						"MALASUGUI",
						"MALATAP",
						"MALAYA",
						"MALIBAGO",
						"MAOT",
						"MASALONG",
						"MATANLANG",
						"NAPAOD",
						"PAG-ASA",
						"PANGPANG",
						"PINYA (POB.)",
						"SAN ANTONIO",
						"SAN FRANCISCO (POB.)",
						"SANTA CRUZ",
						"SUBMAKIN",
						"TALOBATIB",
						"TIGBINAN",
						"TULAY NA LUPA"
					]
				},
				"MERCEDES": {
					"barangay_list": [
						"APUAO",
						"BARANGAY I (POB.)",
						"BARANGAY II (POB.)",
						"BARANGAY III (POB.)",
						"BARANGAY IV (POB.)",
						"BARANGAY V (POB.)",
						"BARANGAY VI (POB.)",
						"BARANGAY VII (POB.)",
						"CARINGO",
						"CATANDUNGANON",
						"CAYUCYUCAN",
						"COLASI",
						"DEL ROSARIO (TAGONGTONG)",
						"GABOC",
						"HAMORAON",
						"HINIPAAN",
						"LALAWIGAN",
						"LANOT",
						"MAMBUNGALON",
						"MANGUISOC",
						"MASALONGSALONG",
						"MATOOGTOOG",
						"PAMBUHAN",
						"QUINAPAGUIAN",
						"SAN ROQUE",
						"TARUM"
					]
				},
				"PARACALE": {
					"barangay_list": [
						"AWITAN",
						"BAGUMBAYAN",
						"BAKAL",
						"BATOBALANI",
						"CALABURNAY",
						"CAPACUAN",
						"CASALUGAN",
						"DAGANG",
						"DALNAC",
						"DANCALAN",
						"GUMAUS",
						"LABNIG",
						"MACOLABO ISLAND",
						"MALACBANG",
						"MALAGUIT",
						"MAMPUNGO",
						"MANGKASAY",
						"MAYBATO",
						"PALANAS",
						"PINAGBIRAYAN MALAKI",
						"PINAGBIRAYAN MUNTI",
						"POBLACION NORTE",
						"POBLACION SUR",
						"TABAS",
						"TALUSAN",
						"TAWIG",
						"TUGOS"
					]
				},
				"SAN LORENZO RUIZ (IMELDA)": {
					"barangay_list": [
						"DACULANG BOLO",
						"DAGOTDOTAN",
						"LANGGA",
						"LANITON",
						"MAISOG",
						"MAMPUROG",
						"MANLIMONSITO",
						"MATACONG (POB.)",
						"SALVACION",
						"SAN ANTONIO",
						"SAN ISIDRO",
						"SAN RAMON"
					]
				},
				"SAN VICENTE": {
					"barangay_list": [
						"ASDUM",
						"CABANBANAN",
						"CALABAGAS",
						"FABRICA",
						"IRAYA SUR",
						"MAN-OGOB",
						"POBLACION DISTRICT I (SILANGAN/BGY. 1)",
						"POBLACION DISTRICT II (KANLURAN/BGY. 2)",
						"SAN JOSE (IRAYA NORTE)"
					]
				},
				"SANTA ELENA": {
					"barangay_list": [
						"BASIAD",
						"BULALA",
						"DON TOMAS",
						"GUITOL",
						"KABULUAN",
						"KAGTALABA",
						"MAULAWIN",
						"PATAG IBABA",
						"PATAG IRAYA",
						"PLARIDEL",
						"POLUNGGUITGUIT",
						"RIZAL",
						"SALVACION",
						"SAN LORENZO",
						"SAN PEDRO",
						"SAN VICENTE",
						"SANTA ELENA (POB.)",
						"TABUGON",
						"VILLA SAN ISIDRO"
					]
				},
				"TALISAY": {
					"barangay_list": [
						"BINANUAAN",
						"CAAWIGAN",
						"CAHABAAN",
						"CALINTAAN",
						"DEL CARMEN",
						"GABON",
						"ITOMANG",
						"POBLACION",
						"SAN FRANCISCO",
						"SAN ISIDRO",
						"SAN JOSE",
						"SAN NICOLAS",
						"SANTA CRUZ",
						"SANTA ELENA",
						"SANTO NIÑO"
					]
				},
				"VINZONS": {
					"barangay_list": [
						"AGUIT-IT",
						"BANOCBOC",
						"BARANGAY I (POB.)",
						"BARANGAY II (POB.)",
						"BARANGAY III (POB.)",
						"CAGBALOGO",
						"CALANGCAWAN NORTE",
						"CALANGCAWAN SUR",
						"GUINACUTAN",
						"MANGCAWAYAN",
						"MANGCAYO",
						"MANLUCUGAN",
						"MATANGO",
						"NAPILIHAN",
						"PINAGTIGASAN",
						"SABANG",
						"SANTO DOMINGO",
						"SINGI",
						"SULA"
					]
				}
			}
		},
		"CAMARINES SUR": {
			"municipality_list": {
				"BAAO": {
					"barangay_list": [
						"AGDANGAN POB. (SAN CAYETANO)",
						"ANTIPOLO",
						"BAGUMBAYAN",
						"BULUANG (SAN ANTONIO)",
						"CARANDAY (LA PURISIMA)",
						"CRISTO REY",
						"DEL PILAR",
						"DEL ROSARIO (POB.)",
						"IYAGAN",
						"LA MEDALLA",
						"LOURDES",
						"NABABARERA",
						"PUGAY (SAN RAFAEL)",
						"SAGRADA",
						"SALVACION",
						"SAN FRANCISCO (POB.)",
						"SAN ISIDRO",
						"SAN JOSE (POB.)",
						"SAN JUAN",
						"SAN NICOLAS (POB.)",
						"SAN RAFAEL (IKPAN)",
						"SAN RAMON (POB.)",
						"SAN ROQUE (POB.)",
						"SAN VICENTE",
						"SANTA CRUZ (POB.)",
						"SANTA EULALIA",
						"SANTA ISABEL",
						"SANTA TERESA (VIGA)",
						"SANTA TERESITA",
						"TAPOL"
					]
				},
				"BALATAN": {
					"barangay_list": [
						"CABANBANAN",
						"CABUNGAN",
						"CAMANGAHAN (CAORASAN)",
						"CAYOGCOG",
						"COGUIT",
						"DURAN",
						"LAGANAC",
						"LULUASAN",
						"MONTENEGRO (MAGUIRON)",
						"PARARAO",
						"PULANG DAGA",
						"SAGRADA NACACALE",
						"SAN FRANCISCO",
						"SANTIAGO NACACALE",
						"SIRAMAG (POB.)",
						"TAPAYAS",
						"TOMATARAYO"
					]
				},
				"BATO": {
					"barangay_list": [
						"AGOS",
						"BACOLOD",
						"BULUANG",
						"CARICOT",
						"CAWACAGAN",
						"COTMON",
						"CRISTO REY",
						"DEL ROSARIO",
						"DIVINA PASTORA (POB.)",
						"GOYUDAN",
						"LOBONG",
						"LUBIGAN",
						"MAINIT",
						"MANGA (MANGGA)",
						"MASOLI",
						"NEIGHBORHOOD",
						"NIÑO JESUS",
						"PAGATPATAN",
						"PALO",
						"PAYAK",
						"SAGRADA (SAGRADA FAMILIA)",
						"SALVACION",
						"SAN ISIDRO (POB.)",
						"SAN JUAN",
						"SAN MIGUEL",
						"SAN RAFAEL (POB.)",
						"SAN ROQUE",
						"SAN VICENTE",
						"SANTA CRUZ (POB.)",
						"SANTIAGO (POB.)",
						"SOOC",
						"TAGPOLO",
						"TRES REYES (POB.)"
					]
				},
				"BOMBON": {
					"barangay_list": [
						"PAGAO (SAN JUAN)",
						"SAN ANTONIO",
						"SAN FRANCISCO",
						"SAN ISIDRO (POB.)",
						"SAN JOSE (POB.)",
						"SAN ROQUE (POB.)",
						"SANTO DOMINGO",
						"SIEMBRE"
					]
				},
				"BUHI": {
					"barangay_list": [
						"AMLONGAN (DEL ROSARIO)",
						"ANTIPOLO",
						"BUROCBUSOC",
						"CABATUAN",
						"CAGMASLOG",
						"DE LA FE",
						"DELOS ANGELES (LOS ANGELES)",
						"DIVINO ROSTRO",
						"GABAS",
						"IBAYUGAN",
						"IGBAC",
						"IPIL (FATIMA)",
						"IRAYA (DEL ROSARIO)",
						"LABAWON (SANTA TERESITA)",
						"LOURDES (SANTA LOURDES)",
						"MACAANGAY",
						"MONTE CALVARIO",
						"NAMURABOD",
						"SAGRADA FAMILIA",
						"SALVACION",
						"SAN ANTONIO",
						"SAN BUENAVENTURA (POB.)",
						"SAN FRANCISCO (PARADA)",
						"SAN ISIDRO",
						"SAN JOSE BAYBAYON",
						"SAN JOSE SALAY",
						"SAN PASCUAL (POB.)",
						"SAN PEDRO (POB.)",
						"SAN RAFAEL",
						"SAN RAMON",
						"SAN ROQUE (POB.)",
						"SAN VICENTE",
						"SANTA CLARA (POB.)",
						"SANTA CRUZ",
						"SANTA ELENA (POB.)",
						"SANTA ISABEL",
						"SANTA JUSTINA",
						"TAMBO"
					]
				},
				"BULA": {
					"barangay_list": [
						"BAGOLADIO",
						"BAGUMBAYAN",
						"BALAOGAN",
						"CAORASAN",
						"CASUGAD",
						"CAUSIP",
						"FABRICA",
						"INOYONAN",
						"ITANGON",
						"KINALABASAHAN",
						"LA PURISIMA",
						"LA VICTORIA",
						"LANIPGA",
						"LUBGAN",
						"OMBAO HEIGHTS",
						"OMBAO POLPOG",
						"PALSONG",
						"PANOYPOYAN",
						"PAWILI",
						"SAGRADA (SAGRADA FAMILIA)",
						"SALVACION (POB.)",
						"SAN AGUSTIN",
						"SAN FRANCISCO",
						"SAN ISIDRO",
						"SAN JOSE",
						"SAN MIGUEL",
						"SAN RAMON",
						"SAN ROQUE (POB.)",
						"SAN ROQUE HEIGHTS",
						"SANTA ELENA",
						"SANTO DOMINGO",
						"SANTO NIÑO",
						"TAISAN"
					]
				},
				"CABUSAO": {
					"barangay_list": [
						"BARCELONITA",
						"BIONG",
						"CAMAGONG",
						"CASTILLO",
						"NEW POBLACION",
						"PANDAN",
						"SAN PEDRO",
						"SANTA CRUZ",
						"SANTA LUTGARDA (POB.)"
					]
				},
				"CALABANGA": {
					"barangay_list": [
						"BALATASAN",
						"BALOMBON",
						"BALONGAY",
						"BELEN",
						"BIGAAS",
						"BINALIW",
						"BINANUAANAN GRANDE",
						"BINANUAANAN PEQUEÑO",
						"BONOT-SANTA ROSA",
						"BURABOD",
						"CABANBANAN",
						"CAGSAO",
						"CAMUNING",
						"COMAGUINGKING",
						"DEL CARMEN (POB.)",
						"DOMINOROG",
						"FABRICA",
						"HAROBAY",
						"LA PURISIMA",
						"LUGSAD",
						"MANGUIRING",
						"PAGATPAT (SAN JOSE)",
						"PAOLBO",
						"PINADA",
						"PUNTA TARAWAL",
						"QUINALE",
						"SABANG",
						"SALVACION-BAYBAY",
						"SAN ANTONIO (QUIPAYO)",
						"SAN ANTONIO POBLACION",
						"SAN BERNARDINO",
						"SAN FRANCISCO (POB.)",
						"SAN ISIDRO",
						"SAN LUCAS",
						"SAN MIGUEL (POB.)",
						"SAN PABLO (POB.)",
						"SAN ROQUE",
						"SAN VICENTE (POB.)",
						"SANTA CRUZ POBLACION",
						"SANTA CRUZ RATAY",
						"SANTA ISABEL (POB.)",
						"SANTA SALUD (POB.)",
						"SANTO DOMINGO",
						"SANTO NIÑO (QUIPAYO)",
						"SIBA-O",
						"SIBOBO",
						"SOGOD",
						"TOMAGODTOD"
					]
				},
				"CAMALIGAN": {
					"barangay_list": [
						"DUGCAL",
						"MARUPIT",
						"SAN FRANCISCO",
						"SAN JOSE-SAN PABLO (POB.)",
						"SAN JUAN-SAN RAMON (POB.)",
						"SAN LUCAS (POB.)",
						"SAN MARCOS (POB.)",
						"SAN MATEO (POB.)",
						"SAN ROQUE",
						"SANTO DOMINGO (POB.)",
						"SANTO TOMAS (POB.)",
						"SUA",
						"TAROSANAN"
					]
				},
				"CANAMAN": {
					"barangay_list": [
						"BARAS (POB.)",
						"DEL ROSARIO",
						"DINAGA (POB.)",
						"FUNDADO",
						"HARING",
						"IQUIN",
						"LINAGA",
						"MANGAYAWAN",
						"PALO",
						"PANGPANG (POB.)",
						"PORO",
						"SAN AGUSTIN",
						"SAN FRANCISCO",
						"SAN JOSE EAST",
						"SAN JOSE WEST",
						"SAN JUAN",
						"SAN NICOLAS",
						"SAN ROQUE",
						"SAN VICENTE",
						"SANTA CRUZ (POB.)",
						"SANTA TERESITA",
						"SUA",
						"TALIDTID",
						"TIBGAO (POB.)"
					]
				},
				"CARAMOAN": {
					"barangay_list": [
						"AGAAS",
						"ANTOLON",
						"BACGONG",
						"BAHAY",
						"BIKAL",
						"BINANUAHAN (POB.)",
						"CABACONGAN",
						"CADONG",
						"CANATUAN",
						"CAPUTATAN",
						"COLONGCOGONG",
						"DARAGA",
						"GATA",
						"GIBGOS",
						"GOGON",
						"GUIJALO",
						"HANOPOL",
						"HANOY",
						"HAPONAN",
						"ILAWOD",
						"ILI-CENTRO (POB.)",
						"LIDONG",
						"LUBAS",
						"MALABOG",
						"MALIGAYA",
						"MAMPIRAO",
						"MANDICLUM (MANDICLOM)",
						"MAQUEDA",
						"MINALABA",
						"ORING",
						"OROC-OSOC",
						"PAGOLINAN",
						"PANDANAN",
						"PANIMAN",
						"PATAG-BELEN",
						"PILI-CENTRO",
						"PILI-TABIGUIAN",
						"POLOAN",
						"SALVACION",
						"SAN ROQUE",
						"SAN VICENTE",
						"SANTA CRUZ",
						"SOLNOPAN",
						"TABGON",
						"TABIGUIAN",
						"TABOG",
						"TAWOG (POB.)",
						"TEROGO",
						"TOBOAN"
					]
				},
				"DEL GALLEGO": {
					"barangay_list": [
						"BAGONG SILANG",
						"BUCAL",
						"CABASAG",
						"COMADAYCADAY",
						"COMADOGCADOG",
						"DOMAGONDONG",
						"KINALANGAN",
						"MABINI",
						"MAGAIS I",
						"MAGAIS II",
						"MANSALAYA",
						"NAGKALIT",
						"PALASPAS",
						"PAMPLONA",
						"PASAY",
						"PINAGDAPIAN",
						"PINUGUSAN",
						"POBLACION ZONE III",
						"SABANG",
						"SALVACION",
						"SAN JUAN",
						"SAN PABLO",
						"SANTA RITA I",
						"SANTA RITA II",
						"SINAGAWSAWAN",
						"SINUKNIPAN I",
						"SINUKNIPAN II",
						"SUGSUGIN",
						"TABION",
						"TOMAGOKTOK",
						"ZONE I FATIMA (POB.)",
						"ZONE II SAN ANTONIO (POB.)"
					]
				},
				"GAINZA": {
					"barangay_list": [
						"CAGBUNGA",
						"DAHILIG",
						"DISTRICT I (POB.)",
						"DISTRICT II (POB.)",
						"LOOB",
						"MALBONG",
						"NAMUAT",
						"SAMPALOC"
					]
				},
				"GARCHITORENA": {
					"barangay_list": [
						"ASON (ANSON)",
						"BAHI",
						"BARANGAY I (POB.)",
						"BARANGAY II (POB.)",
						"BARANGAY III (POB.)",
						"BARANGAY IV (POB.)",
						"BINAGASBASAN",
						"BURABOD",
						"CAGAMUTAN",
						"CAGNIPA",
						"CANLONG",
						"DANGLA",
						"DEL PILAR",
						"DENRICA",
						"HARRISON",
						"MANSANGAT",
						"PAMBUHAN",
						"SAGRADA",
						"SALVACION",
						"SAN VICENTE",
						"SUMAOY",
						"TAMIAWON",
						"TOYTOY"
					]
				},
				"GOA": {
					"barangay_list": [
						"ABUCAYAN",
						"BAGUMBAYAN GRANDE (POB.)",
						"BAGUMBAYAN PEQUEÑO (POB.)",
						"BALAYNAN",
						"BELEN (POB.)",
						"BUYO",
						"CAGAYCAY",
						"CATAGBACAN",
						"DIGDIGON",
						"GIMAGA",
						"HALAWIG-GOGON",
						"HIWACLOY",
						"LA PURISIMA (POB.)",
						"LAMON",
						"MATACLA",
						"MAYMATAN",
						"MAYSALAY",
						"NAPAWON (NAPUNUON)",
						"PANDAY (POB.)",
						"PAYATAN",
						"PINAGLABANAN",
						"SALOG",
						"SAN BENITO (POB.)",
						"SAN ISIDRO (POB.)",
						"SAN ISIDRO WEST",
						"SAN JOSE (POB.)",
						"SAN JUAN BAUTISTA (POB.)",
						"SAN JUAN EVANGELISTA (POB.)",
						"SAN PEDRO (ARORO)",
						"SCOUT FUENTEBELLA",
						"TABGON",
						"TAGONGTONG",
						"TAMBAN (MABINI)",
						"TAYTAY (HALGON EAST)"
					]
				},
				"IRIGA CITY": {
					"barangay_list": [
						"ANTIPOLO",
						"CRISTO REY",
						"DEL ROSARIO (BANAO)",
						"FRANCIA",
						"LA ANUNCIACION",
						"LA MEDALLA",
						"LA PURISIMA",
						"LA TRINIDAD",
						"NIÑO JESUS",
						"PERPETUAL HELP",
						"SAGRADA",
						"SALVACION",
						"SAN AGUSTIN",
						"SAN ANDRES",
						"SAN ANTONIO",
						"SAN FRANCISCO (POB.)",
						"SAN ISIDRO",
						"SAN JOSE",
						"SAN JUAN",
						"SAN MIGUEL",
						"SAN NICOLAS",
						"SAN PEDRO",
						"SAN RAFAEL",
						"SAN RAMON",
						"SAN ROQUE (POB.)",
						"SAN VICENTE NORTE",
						"SAN VICENTE SUR",
						"SANTA CRUZ NORTE",
						"SANTA CRUZ SUR",
						"SANTA ELENA",
						"SANTA ISABEL",
						"SANTA MARIA",
						"SANTA TERESITA",
						"SANTIAGO",
						"SANTO DOMINGO",
						"SANTO NIÑO"
					]
				},
				"LAGONOY": {
					"barangay_list": [
						"AGOSAIS",
						"AGPO-CAMAGONG-TABOG",
						"AMOGUIS",
						"BALATON",
						"BINANUAHAN",
						"BOCOGAN",
						"BURABOD",
						"CABOTONAN",
						"DAHAT",
						"DEL CARMEN",
						"GIMAGTOCON",
						"GINORANGAN (GENORANGAN)",
						"GUBAT",
						"GUIBAHOY",
						"HIMANAG",
						"KINAHOLOGAN",
						"LOHO",
						"MANAMOC",
						"MANGOGON",
						"MAPID",
						"OLAS",
						"OMALO",
						"PANAGAN",
						"PANICUAN",
						"PINAMIHAGAN",
						"SAN FRANCISCO (POB.)",
						"SAN ISIDRO",
						"SAN ISIDRO NORTE (POB.)",
						"SAN ISIDRO SUR (POB.)",
						"SAN RAFAEL",
						"SAN RAMON",
						"SAN ROQUE",
						"SAN SEBASTIAN",
						"SAN VICENTE (POB.)",
						"SANTA CRUZ (POB.)",
						"SANTA MARIA (POB.)",
						"SARIPONGPONG (POB.)",
						"SIPACO"
					]
				},
				"LIBMANAN": {
					"barangay_list": [
						"ASLONG",
						"AWAYAN",
						"BAGACAY",
						"BAGADION",
						"BAGAMELON",
						"BAGUMBAYAN",
						"BAHAO",
						"BAHAY",
						"BEGAJO NORTE",
						"BEGAJO SUR",
						"BEGUITO NUEVO",
						"BEGUITO VIEJO",
						"BIKAL",
						"BUSAK",
						"CAIMA",
						"CALABNIGAN",
						"CAMAMBUGAN",
						"CAMBALIDIO",
						"CANDAMI",
						"CANDATO",
						"CAWAYAN",
						"CONCEPCION",
						"CUYAPI",
						"DANAWAN",
						"DUANG NIOG",
						"HANDONG",
						"IBID",
						"INALAHAN",
						"LABAO",
						"LIBOD I",
						"LIBOD II",
						"LOBA-LOBA",
						"MABINI",
						"MALANSAD NUEVO",
						"MALANSAD VIEJO",
						"MALBOGON",
						"MALINAO",
						"MAMBALITE",
						"MAMBAYAWAS",
						"MAMBULO NUEVO",
						"MAMBULO VIEJO",
						"MANCAWAYAN",
						"MANDACANAN",
						"MANTALISAY",
						"PADLOS",
						"PAG-ORING NUEVO",
						"PAG-ORING VIEJO",
						"PALANGON",
						"PALONG",
						"PATAG",
						"PLANZA",
						"POBLACION",
						"POTOT",
						"PURO-BATIA",
						"RONGOS",
						"SALVACION",
						"SAN ISIDRO",
						"SAN JUAN",
						"SAN PABLO",
						"SAN VICENTE",
						"SIBUJO",
						"SIGAMOT",
						"STATION-CHURCH SITE",
						"TABAN-FUNDADO",
						"TAMPUHAN",
						"TANAG",
						"TARUM",
						"TINALMUD NUEVO",
						"TINALMUD VIEJO",
						"TINANGKIHAN",
						"UDOC",
						"UMALO",
						"USON",
						"VILLADIMA (SANTA CRUZ)",
						"VILLASOCORRO"
					]
				},
				"LUPI": {
					"barangay_list": [
						"ALLEOMAR",
						"BAGANGAN SR.",
						"BAGONG SIKAT",
						"BANGON",
						"BARRERA JR.",
						"BARRERA SR.",
						"BEL-CRUZ",
						"BELWANG",
						"BUENASUERTE",
						"BULAWAN JR.",
						"BULAWAN SR.",
						"CABUTAGAN",
						"CASAY",
						"COLACLING (DEL ROSARIO)",
						"CRISTO REY",
						"DEL CARMEN",
						"HAGUIMIT",
						"HALUBAN (PIGBASAGAN)",
						"KAIBIGAN",
						"LA PURISIMA",
						"LOURDES",
						"MANGCAWAYAN",
						"NAPOLIDAN",
						"POBLACION",
						"POLANTUNA",
						"SAGRADA",
						"SALVACION",
						"SAN ISIDRO",
						"SAN JOSE",
						"SAN PEDRO",
						"SAN RAFAEL NORTE",
						"SAN RAFAEL SUR",
						"SAN RAMON",
						"SAN VICENTE",
						"SOOC",
						"TANAWAN",
						"TAPI (LUPI NUEVO)",
						"TIBLE"
					]
				},
				"MAGARAO": {
					"barangay_list": [
						"BAROBAYBAY",
						"BELL (POB.)",
						"CARANGCANG",
						"CARIGSA",
						"CASURAY",
						"MONSERRAT (POB.)",
						"PONONG",
						"SAN FRANCISCO (POB.)",
						"SAN ISIDRO (POB.)",
						"SAN JUAN (POB.)",
						"SAN MIGUEL",
						"SAN PANTALEON (POB.)",
						"SANTA LUCIA (POB.)",
						"SANTA ROSA",
						"SANTO TOMAS (POB.)"
					]
				},
				"MILAOR": {
					"barangay_list": [
						"ALIMBUYOG",
						"AMPARADO (POB.)",
						"BALAGBAG",
						"BORONGBORONGAN",
						"CABUGAO",
						"CAPUCNASAN",
						"DALIPAY",
						"DEL ROSARIO (POB.)",
						"FLORDELIZ",
						"LIPOT",
						"MAYAOPAYAWAN",
						"MAYCATMON",
						"MAYDASO",
						"SAN ANTONIO",
						"SAN JOSE (POB.)",
						"SAN MIGUEL (POB.)",
						"SAN ROQUE (POB.)",
						"SAN VICENTE (POB.)",
						"SANTO DOMINGO (POB.)",
						"TARUSANAN"
					]
				},
				"MINALABAC": {
					"barangay_list": [
						"ANTIPOLO",
						"BAGOLATAO",
						"BAGONGBONG",
						"BALIUAG NUEVO",
						"BALIUAG VIEJO",
						"CATANUSAN",
						"DEL CARMEN-DEL ROSARIO (POB.)",
						"DEL SOCORRO",
						"HAMORAON",
						"HOBO",
						"IRAYANG SOLONG",
						"MAGADAP",
						"MALITBOG",
						"MANAPAO",
						"MATAOROC",
						"SAGRADA (SAGRADA FAMILIA)",
						"SALINGOGON",
						"SAN ANTONIO",
						"SAN FELIPE-SANTIAGO (POB.)",
						"SAN FRANCISCO (POB.)",
						"SAN JOSE",
						"SAN JUAN-SAN LORENZO (POB.)",
						"TABAN",
						"TARIRIC",
						"TIMBANG"
					]
				},
				"NABUA": {
					"barangay_list": [
						"ANGUSTIA (ANGUSTIA INAPATAN)",
						"ANTIPOLO OLD",
						"ANTIPOLO YOUNG",
						"ARO-ALDAO",
						"BUSTRAC",
						"DOLOROSA (DOLOROSA INAPATAN)",
						"DURAN (JESUS DURAN)",
						"INAPATAN (DEL ROSARIO INAPATAN)",
						"LA OPINION",
						"LA PURISIMA (LA PURISIMA AGUPIT)",
						"LOURDES OLD",
						"LOURDES YOUNG",
						"MALAWAG (SAN JOSE MALAWAG)",
						"PALOYON ORIENTAL",
						"PALOYON PROPER (SAGRADA PALOYON)",
						"SALVACION QUE GATOS",
						"SAN ANTONIO (POB.)",
						"SAN ANTONIO OGBON",
						"SAN ESTEBAN (POB.)",
						"SAN FRANCISCO (POB.)",
						"SAN ISIDRO (POB.)",
						"SAN ISIDRO INAPATAN",
						"SAN JOSE (SAN JOSE PANGARAON)",
						"SAN JUAN (POB.)",
						"SAN LUIS (POB.)",
						"SAN MIGUEL (POB.)",
						"SAN NICOLAS (POB.)",
						"SAN ROQUE (POB.)",
						"SAN ROQUE MADAWON",
						"SAN ROQUE SAGUMAY",
						"SAN VICENTE GORONG-GORONG",
						"SAN VICENTE OGBON",
						"SANTA BARBARA (MALIBAN)",
						"SANTA CRUZ",
						"SANTA ELENA BARAS",
						"SANTA LUCIA BARAS",
						"SANTIAGO OLD",
						"SANTIAGO YOUNG",
						"SANTO DOMINGO",
						"TANDAAY",
						"TOPAS PROPER",
						"TOPAS SOGOD"
					]
				},
				"NAGA CITY": {
					"barangay_list": [
						"ABELLA",
						"BAGUMBAYAN NORTE",
						"BAGUMBAYAN SUR",
						"BALATAS",
						"CALAUAG",
						"CARARAYAN",
						"CAROLINA",
						"CONCEPCION GRANDE",
						"CONCEPCION PEQUEÑO",
						"DAYANGDANG",
						"DEL ROSARIO",
						"DINAGA",
						"IGUALDAD INTERIOR",
						"LERMA",
						"LIBOTON",
						"MABOLO",
						"PACOL",
						"PANICUASON",
						"PEÑAFRANCIA",
						"SABANG",
						"SAN FELIPE",
						"SAN FRANCISCO (POB.)",
						"SAN ISIDRO",
						"SANTA CRUZ",
						"TABUCO",
						"TINAGO",
						"TRIANGULO"
					]
				},
				"OCAMPO": {
					"barangay_list": [
						"AYUGAN",
						"CABARIWAN",
						"CAGMANABA",
						"DEL ROSARIO",
						"GATBO",
						"GUINABAN",
						"HANAWAN",
						"HIBAGO",
						"LA PURISIMA NUEVO",
						"MAY-OGOB",
						"NEW MORIONES",
						"OLD MORIONES",
						"PINIT",
						"POBLACION CENTRAL",
						"POBLACION EAST",
						"POBLACION WEST",
						"SALVACION",
						"SAN ANTONIO",
						"SAN FRANCISCO",
						"SAN JOSE ORAS",
						"SAN ROQUE COMMONAL",
						"SAN VICENTE",
						"SANTA CRUZ",
						"SANTO NIÑO",
						"VILLAFLORIDA"
					]
				},
				"PAMPLONA": {
					"barangay_list": [
						"BATANG",
						"BURABOD",
						"CAGBIBI",
						"CAGBUNGA",
						"CALAWAT",
						"DEL ROSARIO",
						"PATONG",
						"POBLACION",
						"SALVACION",
						"SAN GABRIEL",
						"SAN ISIDRO",
						"SAN RAFAEL",
						"SAN RAMON",
						"SAN VICENTE",
						"TAMBO",
						"TAMPADONG",
						"VENERACION (TAGUILID)"
					]
				},
				"PASACAO": {
					"barangay_list": [
						"ANTIPOLO",
						"BAGONG SILANG",
						"BAHAY",
						"BALOGO",
						"CARANAN",
						"CUCO",
						"DALUPAON",
						"HUBO",
						"ITULAN",
						"MACAD (HEBRIO LOURDES)",
						"ODICON",
						"QUITANG",
						"SALVACION",
						"SAN ANTONIO",
						"SAN CIRILO (POB.)",
						"SANTA ROSA DEL NORTE (POB.)",
						"SANTA ROSA DEL SUR (POB.)",
						"TILNAC",
						"TINALMUD"
					]
				},
				"PILI": {
					"barangay_list": [
						"ANAYAN",
						"BAGONG SIRANG",
						"BINANWAANAN",
						"BINOBONG",
						"CADLAN",
						"CAROYROYAN",
						"CURRY",
						"DEL ROSARIO",
						"HIMAAO",
						"LA PURISIMA",
						"NEW SAN ROQUE",
						"OLD SAN ROQUE (POB.)",
						"PALESTINA",
						"PAWILI",
						"SAGRADA",
						"SAGURONG",
						"SAN AGUSTIN",
						"SAN ANTONIO (POB.)",
						"SAN ISIDRO (POB.)",
						"SAN JOSE",
						"SAN JUAN (POB.)",
						"SAN VICENTE (POB.)",
						"SANTIAGO (POB.)",
						"SANTO NIÑO",
						"TAGBONG",
						"TINANGIS"
					]
				},
				"PRESENTACION (PARUBCAN)": {
					"barangay_list": [
						"AYUGAO",
						"BAGONG SIRANG",
						"BALIGUIAN",
						"BANTUGAN",
						"BICALEN",
						"BITAOGAN",
						"BUENAVISTA",
						"BULALACAO",
						"CAGNIPA",
						"LAGHA",
						"LIDONG",
						"LIWACSA",
						"MAANGAS",
						"PAGSANGAHAN",
						"PATROCINIO",
						"PILI",
						"SANTA MARIA (POB.)",
						"TANAWAN"
					]
				},
				"RAGAY": {
					"barangay_list": [
						"AGAO-AO",
						"AGRUPACION",
						"AMOMOKPOK",
						"APAD",
						"APALE",
						"BANGA CAVES",
						"BAYA",
						"BINAHAN PROPER",
						"BINAHAN UPPER",
						"BUENASUERTE",
						"CABADISAN",
						"CABINITAN",
						"CABUGAO",
						"CADITAAN",
						"CALE",
						"CATABANGAN PROPER",
						"F. SIMEON (PUGOD)",
						"GODOFREDO REYES SR. (CATABANGAN CROSSING)",
						"INANDAWA",
						"LAGUIO",
						"LANIPGA-CAWAYAN",
						"LIBORO",
						"LOHONG",
						"LOWER OMON",
						"LOWER SANTA CRUZ",
						"PANAYTAYAN",
						"PANAYTAYAN NUEVO",
						"PATALUNAN",
						"POBLACION ILAOD",
						"POBLACION IRAYA",
						"PORT JUNCTION NORTE",
						"PORT JUNCTION SUR",
						"SALVACION",
						"SAMAY",
						"SAN RAFAEL",
						"TAGBAC",
						"UPPER OMON",
						"UPPER SANTA CRUZ"
					]
				},
				"SAGÑAY": {
					"barangay_list": [
						"ANIOG",
						"ATULAYAN",
						"BONGALON",
						"BURACAN",
						"CATALOTOAN",
						"DEL CARMEN (POB.)",
						"KILANTAAO",
						"KILOMAON",
						"MABCA",
						"MINADONGJOL",
						"NATO",
						"PATITINAN",
						"SAN ANTONIO (POB.)",
						"SAN ISIDRO (POB.)",
						"SAN ROQUE (POB.)",
						"SANTO NIÑO",
						"SIBAGUAN",
						"TINORONGAN",
						"TURAGUE"
					]
				},
				"SAN FERNANDO": {
					"barangay_list": [
						"ALIANZA",
						"BEBERON",
						"BICAL",
						"BOCAL",
						"BONIFACIO (POB.)",
						"BUENAVISTA (POB.)",
						"CALASCAGAS",
						"COTMO",
						"DACULANG TUBIG",
						"DEL PILAR (POB.)",
						"GÑARAN",
						"GRIJALVO",
						"LUPI",
						"MARAGÑI",
						"PAMUKID",
						"PINAMASAGAN",
						"PIPIAN",
						"PLANZA",
						"RIZAL (POB.)",
						"SAN JOAQUIN",
						"SANTA CRUZ",
						"TAGPOCOL"
					]
				},
				"SAN JOSE": {
					"barangay_list": [
						"ADIANGAO",
						"BAGACAY",
						"BAHAY",
						"BOCLOD",
						"CALALAHAN",
						"CALAWIT",
						"CAMAGONG",
						"CATALOTOAN",
						"DANLOG",
						"DEL CARMEN (POB.)",
						"DOLO",
						"KINALANSAN",
						"MAMPIRAO",
						"MANZANA",
						"MINORO",
						"PALALE",
						"PONGLON",
						"PUGAY",
						"SABANG",
						"SALOGON",
						"SAN ANTONIO (POB.)",
						"SAN JUAN (POB.)",
						"SAN VICENTE (POB.)",
						"SANTA CRUZ (POB.)",
						"SOLEDAD (POB.)",
						"TAGAS",
						"TAMBANGAN",
						"TELEGRAFO",
						"TOMINAWOG"
					]
				},
				"SIPOCOT": {
					"barangay_list": [
						"ALDEZAR",
						"ALTEZA",
						"ANIB",
						"AWAYAN",
						"AZUCENA",
						"BAGONG SIRANG",
						"BINAHIAN",
						"BOLO NORTE",
						"BOLO SUR",
						"BULAN",
						"BULAWAN",
						"CABUYAO",
						"CAIMA",
						"CALAGBANGAN",
						"CALAMPINAY",
						"CARAYRAYAN",
						"COTMO",
						"GABI",
						"GAONGAN",
						"IMPIG",
						"LIPILIP",
						"LUBIGAN JR.",
						"LUBIGAN SR.",
						"MALAGUICO",
						"MALUBAGO",
						"MANANGLE",
						"MANGAPO",
						"MANGGA",
						"MANLUBANG",
						"MANTILA",
						"NORTH CENTRO (POB.)",
						"NORTH VILLAZAR",
						"SAGRADA FAMILIA",
						"SALANDA",
						"SALVACION",
						"SAN ISIDRO",
						"SAN VICENTE",
						"SERRANZANA",
						"SOUTH CENTRO (POB.)",
						"SOUTH VILLAZAR",
						"TAISAN",
						"TARA",
						"TIBLE",
						"TULA-TULA",
						"VIGAAN",
						"YABO"
					]
				},
				"SIRUMA": {
					"barangay_list": [
						"BAGONG SIRANG",
						"BAHAO",
						"BOBOAN",
						"BUTAWANAN",
						"CABUGAO",
						"FUNDADO",
						"HOMESTEAD",
						"LA PURISIMA",
						"MABUHAY",
						"MALACONINI",
						"MATANDANG SIRUMA",
						"NALAYAHAN",
						"PAMINTAN-BANTILAN",
						"PINITAN",
						"POBLACION",
						"SALVACION",
						"SAN ANDRES",
						"SAN RAMON (DALDAGON)",
						"SULPA",
						"TANDOC",
						"TONGO-BANTIGUE",
						"VITO"
					]
				},
				"TIGAON": {
					"barangay_list": [
						"ABO",
						"CABALINADAN",
						"CARAYCAYON",
						"CASUNA",
						"CONSOCEP",
						"COYAOYAO",
						"GAAO",
						"GINGAROY",
						"GUBAT",
						"HUYONHUYON",
						"LIBOD",
						"MABALODBALOD",
						"MAY-ANAO",
						"PANAGAN",
						"POBLACION",
						"SALVACION",
						"SAN ANTONIO",
						"SAN FRANCISCO",
						"SAN MIGUEL",
						"SAN RAFAEL",
						"TALOJONGON",
						"TINAWAGAN",
						"VINAGRE"
					]
				},
				"TINAMBAC": {
					"barangay_list": [
						"AGAY-AYAN",
						"ANTIPOLO",
						"BAGACAY",
						"BANGA",
						"BANI",
						"BATAAN",
						"BINALAY",
						"BOLAOBALITE",
						"BUENAVISTA",
						"BUYO",
						"CAGLILIOG",
						"CALOCO",
						"CAMAGONG",
						"CANAYONAN",
						"CAWAYNAN",
						"DALIGAN",
						"FILARCA (POB.)",
						"LA MEDALLA (MILE 9)",
						"LA PURISIMA (POB.)",
						"LUPI",
						"MAGSAYSAY (CAMP 4)",
						"MAGTANG",
						"MANANAO",
						"NEW CAALUAN",
						"OLAG GRANDE",
						"OLAG PEQUEÑO",
						"OLD CAALUAN",
						"PAG-ASA",
						"PANTAT",
						"SAGRADA (CAMP 6)",
						"SALVACION",
						"SALVACION POBLACION",
						"SAN ANTONIO",
						"SAN ISIDRO (POB.)",
						"SAN JOSE (TILTILAN)",
						"SAN PASCUAL (POB.)",
						"SAN RAMON (CAMP 7)",
						"SAN ROQUE",
						"SAN VICENTE",
						"SANTA CRUZ (POB.)",
						"SOGOD",
						"TAMBANG",
						"TIERRA NEVADA",
						"UNION"
					]
				}
			}
		},
		"CATANDUANES": {
			"municipality_list": {
				"BAGAMANOC": {
					"barangay_list": [
						"ANTIPOLO",
						"BACAK",
						"BAGATABAO",
						"BUGAO",
						"CAHAN",
						"HINIPAAN",
						"MAGSAYSAY",
						"POBLACION",
						"QUEZON (PANCAYANAN)",
						"QUIGARAY",
						"SAGRADA",
						"SALVACION (PANUTO)",
						"SAN ISIDRO",
						"SAN RAFAEL (MAHANTOD)",
						"SAN VICENTE",
						"SANTA MESA",
						"SANTA TERESA",
						"SUCHAN"
					]
				},
				"BARAS": {
					"barangay_list": [
						"ABIHAO",
						"AGBAN",
						"BAGONG SIRANG",
						"BATOLINAO",
						"BENTICAYAN",
						"BUENAVISTA",
						"CARAGUMIHAN",
						"DANAO",
						"EASTERN POBLACION",
						"GINITLIGAN",
						"GUINSAANAN",
						"J. M. ALBERTO",
						"MACUTAL",
						"MONING",
						"NAGBARORONG",
						"OSMEÑA",
						"P. TESTON",
						"PANIQUIHAN",
						"PURARAN",
						"PUTSAN",
						"QUEZON",
						"RIZAL",
						"SAGRADA",
						"SALVACION",
						"SAN LORENZO",
						"SAN MIGUEL",
						"SANTA MARIA",
						"TILOD",
						"WESTERN POBLACION"
					]
				},
				"BATO": {
					"barangay_list": [
						"AROYAO PEQUEÑO",
						"BAGUMBAYAN",
						"BANAWANG",
						"BATALAY",
						"BINANUAHAN",
						"BOTE",
						"BUENAVISTA",
						"CABUGAO",
						"CAGRARAY",
						"CARORIAN",
						"GUINOBATAN",
						"ILAWOD (POB.)",
						"LIBJO",
						"LIBOD POBLACION",
						"MARINAWA",
						"MINTAY",
						"OGUIS",
						"PANANAOGAN",
						"SAN ANDRES",
						"SAN PEDRO",
						"SAN ROQUE",
						"SANTA ISABEL",
						"SIBACUNGAN",
						"SIPI",
						"TALISAY",
						"TAMBURAN",
						"TILIS"
					]
				},
				"CARAMORAN": {
					"barangay_list": [
						"BAYBAY (POB.)",
						"BOCON",
						"BOTHOAN (POB.)",
						"BUENAVISTA",
						"BULALACAO",
						"CAMBURO",
						"DARIAO",
						"DATAG EAST",
						"DATAG WEST",
						"GUIAMLONG",
						"HITOMA",
						"ICANBATO (POB.)",
						"INALMASINAN",
						"IYAO",
						"MABINI",
						"MAUI",
						"MAYSURAN",
						"MILAVIGA",
						"OBI",
						"PANIQUE",
						"SABANGAN",
						"SABLOYON",
						"SALVACION",
						"SUPANG",
						"TOYTOY (POB.)",
						"TUBLI",
						"TUCAO"
					]
				},
				"GIGMOTO": {
					"barangay_list": [
						"BIONG",
						"DORORIAN",
						"POBLACION DISTRICT I",
						"POBLACION DISTRICT II",
						"POBLACION DISTRICT III",
						"SAN PEDRO",
						"SAN VICENTE",
						"SICMIL",
						"SIORON"
					]
				},
				"PANDAN": {
					"barangay_list": [
						"BAGAWANG",
						"BALAGÑONAN",
						"BALDOC",
						"CANLUBI",
						"CATAMBAN",
						"COBO",
						"HIYOP",
						"LIBOD (POB.)",
						"LOURDES",
						"LUMABAO",
						"MARAMBONG",
						"NAPO (POB.)",
						"OGA",
						"PANDAN DEL NORTE (POB.)",
						"PANDAN DEL SUR (POB.)",
						"PANUTO",
						"POROT (SAN JOSE)",
						"SALVACION (TARIWARA)",
						"SAN ANDRES (DINUNGSURAN)",
						"SAN ISIDRO (LANGOB)",
						"SAN RAFAEL (BOGTONG)",
						"SAN ROQUE",
						"SANTA CRUZ (CATAGBACAN)",
						"TABUGOC",
						"TOKIO",
						"WAGDAS"
					]
				},
				"PANGANIBAN (PAYO)": {
					"barangay_list": [
						"ALINAWAN",
						"BABAGUAN",
						"BAGONG BAYAN",
						"BURABOD",
						"CABUYOAN",
						"CAGDARAO",
						"MABINI",
						"MACULIW",
						"PANAY",
						"SALVACION (POB.)",
						"SAN ANTONIO",
						"SAN JOAQUIN (POB.)",
						"SAN JOSE (POB.)",
						"SAN JUAN (POB.)",
						"SAN MIGUEL",
						"SAN NICOLAS (POB.)",
						"SAN PEDRO (POB.)",
						"SAN VICENTE (POB.)",
						"SANTA ANA (POB.)",
						"SANTA MARIA (POB.)",
						"SANTO SANTIAGO (POB.)",
						"TAOPON (PANGCAYANAN)",
						"TIBO"
					]
				},
				"SAN ANDRES (CALOLBON)": {
					"barangay_list": [
						"AGOJO",
						"ALIBUAG",
						"ASGAD (JUAN M. ALBERTO)",
						"BAGONG SIRANG",
						"BARIHAY",
						"BATONG PALOWAY",
						"BELMONTE (POB.)",
						"BISLIG",
						"BON-OT",
						"CABCAB",
						"CABUNGAHAN",
						"CARANGAG",
						"CATAGBACAN",
						"CODON",
						"COMAGAYCAY",
						"DATAG",
						"DIVINO ROSTRO (POB.)",
						"ESPERANZA (POB.)",
						"HILAWAN",
						"LICTIN",
						"LUBAS",
						"MANAMBRAG",
						"MAYNGAWAY",
						"PALAWIG",
						"PUTING BAYBAY",
						"RIZAL",
						"SALVACION (POB.)",
						"SAN ISIDRO",
						"SAN JOSE",
						"SAN ROQUE (POB.)",
						"SAN VICENTE",
						"SANTA CRUZ (POB.)",
						"SAPANG PALAY (POB.)",
						"TIBANG",
						"TIMBAAN",
						"TOMINAWOG",
						"WAGDAS (POB.)",
						"YOCTI"
					]
				},
				"SAN MIGUEL": {
					"barangay_list": [
						"ATSAN (DISTRICT I)",
						"BALATOHAN",
						"BOTON",
						"BUHI",
						"DAYAWA",
						"J. M. ALBERTO",
						"KATIPUNAN",
						"KILIKILIHAN",
						"MABATO",
						"OBO",
						"PACOGON",
						"PAGSANGAHAN",
						"PANGILAO",
						"PARAISO",
						"POBLACION DISTRICT II",
						"POBLACION DISTRICT III",
						"PROGRESO",
						"SALVACION (PATAGAN)",
						"SAN JUAN (AROYAO)",
						"SAN MARCOS",
						"SANTA ELENA (PATAGAN)",
						"SIAY",
						"SOLONG",
						"TOBREHON"
					]
				},
				"VIGA": {
					"barangay_list": [
						"ALMOJUELA",
						"ANANONG",
						"ASUNCION (POB.)",
						"BATOHONAN",
						"BEGONIA",
						"BOTINAGAN",
						"BUENAVISTA",
						"BURGOS",
						"DEL PILAR",
						"MABINI",
						"MAGSAYSAY",
						"OGBONG",
						"OSMEÑA",
						"PEDRO VERA (SUMMIT)",
						"PEÑAFRANCIA (POB.)",
						"QUEZON",
						"QUIRINO (ABUGAN)",
						"RIZAL",
						"ROXAS",
						"SAGRADA",
						"SAN ISIDRO (POB.)",
						"SAN JOSE OCO",
						"SAN JOSE POBLACION",
						"SAN PEDRO (POB.)",
						"SAN ROQUE (POB.)",
						"SAN VICENTE (POB.)",
						"SANTA ROSA",
						"SOBOC",
						"TAMBONGON",
						"TINAGO",
						"VILLA AURORA"
					]
				},
				"VIRAC": {
					"barangay_list": [
						"ANTIPOLO DEL NORTE",
						"ANTIPOLO DEL SUR",
						"BALITE",
						"BATAG",
						"BIGAA",
						"BUENAVISTA",
						"BUYO",
						"CABIHIAN",
						"CALABNIGAN",
						"CALAMPONG",
						"CALATAGAN PROPER",
						"CALATAGAN TIBANG",
						"CAPILIHAN",
						"CASOOCAN",
						"CAVINITAN",
						"CONCEPCION (POB.)",
						"CONSTANTINO (POB.)",
						"DANICOP",
						"DUGUI SAN ISIDRO",
						"DUGUI SAN VICENTE",
						"DUGUI TOO",
						"F. TACORDA VILLAGE",
						"FRANCIA (POB.)",
						"GOGON CENTRO",
						"GOGON SIRANGAN",
						"HAWAN GRANDE",
						"HAWAN ILAYA",
						"HICMING",
						"IBONG SAPA (SAN VICENTE SUR)",
						"IGANG",
						"JUAN M. ALBERTO (PONITON)",
						"LANAO (POB.)",
						"MAGNESIA DEL NORTE",
						"MAGNESIA DEL SUR",
						"MARCELO ALBERTO (POB.)",
						"MARILIMA",
						"PAJO BAGUIO",
						"PAJO SAN ISIDRO",
						"PALNAB DEL NORTE",
						"PALNAB DEL SUR",
						"PALTA BIG",
						"PALTA SALVACION",
						"PALTA SMALL",
						"RAWIS (POB.)",
						"SALVACION",
						"SAN ISIDRO VILLAGE",
						"SAN JOSE (POB.)",
						"SAN JUAN (POB.)",
						"SAN PABLO (POB.)",
						"SAN PEDRO (POB.)",
						"SAN ROQUE (POB.)",
						"SAN VICENTE",
						"SANTA CRUZ",
						"SANTA ELENA (POB.)",
						"SANTO CRISTO",
						"SANTO DOMINGO",
						"SANTO NIÑO",
						"SIMAMLA",
						"SOGOD-SIMAMLA",
						"SOGOD-TIBGAO",
						"TALISOY",
						"TUBAON",
						"VALENCIA"
					]
				}
			}
		},
		"MASBATE": {
			"municipality_list": {
				"AROROY": {
					"barangay_list": [
						"AMBOLONG",
						"AMOROY",
						"AMUTAG",
						"BAGAUMA",
						"BALAWING",
						"BALETE",
						"BANGON",
						"CABANGCALAN",
						"CABAS-AN",
						"CALANAY",
						"CAPSAY",
						"CONCEPCION",
						"DAYHAGAN",
						"DON PABLO DELA ROSA",
						"GUMAHANG",
						"JABOYOAN",
						"LANANG",
						"LUY-A",
						"MACABUG",
						"MALUBI",
						"MANAGANAGA",
						"MANAMOC",
						"MARIPOSA",
						"MATABA",
						"MATALANGTALANG",
						"MATANGOG",
						"NABONGSORAN",
						"PANGLE",
						"PANIQUE",
						"PINANAAN",
						"POBLACION",
						"PURO",
						"SAN AGUSTIN",
						"SAN ISIDRO",
						"SAWANG",
						"SYNDICATE",
						"TALABAAN",
						"TALIB",
						"TIGBAO",
						"TINAGO",
						"TINIGBAN"
					]
				},
				"BALENO": {
					"barangay_list": [
						"BAAO",
						"BANASE",
						"BATUILA",
						"CAGARA",
						"CAGPANDAN",
						"CANCAHORAO",
						"CANJUNDAY",
						"DOCOL",
						"EASTERN CAPSAY",
						"GABI",
						"GANGAO",
						"LAGTA",
						"LAHONG INTERIOR",
						"LAHONG PROPER",
						"LIPATA",
						"MADANGCALAN",
						"MAGDALENA",
						"MANOBOC",
						"OBONGON DIOT",
						"POBLACION",
						"POLOT",
						"POTOSON",
						"SOG-ONG",
						"TINAPIAN"
					]
				},
				"BALUD": {
					"barangay_list": [
						"BAYBAY (LUMOCAB)",
						"BONGCANAWAY",
						"CALUMPANG",
						"CANTIL",
						"CASAMONGAN",
						"DANAO",
						"DAO",
						"GUINBANWAHAN",
						"ILAYA",
						"JANGAN",
						"JINTOTOLO",
						"MABUHAY (BONGCANAWAY III)",
						"MAPILI",
						"MAPITOGO",
						"PAJO",
						"PALANE",
						"PANGUIRANAN",
						"PANUBIGAN",
						"POBLACION (BALUD)",
						"PULANDUTA",
						"QUINAYANGAN DIOTAY",
						"QUINAYANGAN TONGA",
						"SALVACION",
						"SAMPAD",
						"SAN ANDRES (QUINAYANGAN DACU)",
						"SAN ANTONIO",
						"SAPATOS",
						"TALISAY",
						"TONGA",
						"UBO",
						"VICTORY (VICTORIA)",
						"VILLA ALVAREZ"
					]
				},
				"BATUAN": {
					"barangay_list": [
						"BURGOS",
						"CAMBAÑEZ",
						"CANARES",
						"COSTA RICA",
						"DANAO",
						"GIBRALTAR",
						"MABUHAY",
						"MATABAO",
						"NASANDIG",
						"PANISIHAN",
						"POBLACION",
						"RIZAL",
						"ROYROY",
						"SAWANG"
					]
				},
				"CATAINGAN": {
					"barangay_list": [
						"ABACA",
						"AGUADA",
						"BADIANG",
						"BAGUMBAYAN",
						"CADULAWAN",
						"CAGBATANG",
						"CHIMENEA",
						"CONCEPCION",
						"CURVADA",
						"DIVISORIA",
						"DOMOROG",
						"ESTAMPAR",
						"GAHIT",
						"LIBTONG",
						"LIONG",
						"MAANAHAO",
						"MADAMBA",
						"MALOBAGO",
						"MATAYUM",
						"MATUBINAO",
						"MINTAC",
						"NADAWISAN",
						"OSMEÑA",
						"PAWICAN",
						"PITOGO",
						"POBLACION",
						"QUEZON",
						"SAN ISIDRO",
						"SAN JOSE",
						"SAN PEDRO",
						"SAN RAFAEL",
						"SANTA TERESITA",
						"SANTO NIÑO",
						"TAGBOAN",
						"TUYBO",
						"VILLA POGADO"
					]
				},
				"CAWAYAN": {
					"barangay_list": [
						"BEGIA",
						"CABAYUGAN",
						"CABUNGAHAN",
						"CALAPAYAN",
						"CALUMPANG",
						"CHICO ISLAND",
						"DALIPE",
						"DIVISORIA",
						"GILOTONGAN",
						"GUIOM",
						"IRAYA",
						"ITOMBATO",
						"LAGUE-LAGUE",
						"LIBERTAD",
						"LOOC",
						"MACTAN",
						"MADBAD",
						"MAHAYAHAY",
						"MAIHAO",
						"MALBUG",
						"NARO",
						"PALOBANDERA",
						"PANANAWAN",
						"PEÑA ISLAND",
						"PIN-AS",
						"POBLACION",
						"PULOT",
						"PUNTA BATSAN",
						"R.M. MAGBALON (BEBINAN)",
						"RECODO",
						"SAN JOSE",
						"SAN VICENTE",
						"TABERNA",
						"TALISAY",
						"TUBOG",
						"TUBURAN",
						"VILLAHERMOSA"
					]
				},
				"CLAVERIA": {
					"barangay_list": [
						"ALBASAN",
						"BOCA ENGAÑO",
						"BUYO",
						"CALPI",
						"CANOMAY",
						"CAWAYAN",
						"IMELDA",
						"MABABANG BAYBAY",
						"MABITON",
						"MANAPAO",
						"NABASAGAN",
						"NONOC",
						"OSMEÑA",
						"PASIG",
						"PEÑAFRANCIA",
						"POBLACION DISTRICT I (BGY. 1)",
						"POBLACION DISTRICT II (BGY. 2)",
						"QUEZON",
						"SAN ISIDRO",
						"SAN RAMON",
						"SAN VICENTE",
						"TAGUILID"
					]
				},
				"DIMASALANG": {
					"barangay_list": [
						"BALANTAY",
						"BALOCAWE",
						"BANAHAO",
						"BUENAFLOR",
						"BURACAN",
						"CABANOYOAN",
						"CABRERA",
						"CADULAN",
						"CALABAD",
						"CANOMAY",
						"DIVISORIA",
						"GAID",
						"GREGORIO ALINO (PIA-ONG)",
						"MAGCARAGUIT",
						"MAMBOG",
						"POBLACION",
						"RIZAL",
						"SAN VICENTE",
						"SUBA",
						"T.R. YANGCO (YANCO)"
					]
				},
				"ESPERANZA": {
					"barangay_list": [
						"AGOHO",
						"ALMERO",
						"BARAS",
						"DOMOROG",
						"GUADALUPE",
						"ILIGAN",
						"LABANGTAYTAY",
						"LABRADOR",
						"LIBERTAD",
						"MAGSAYSAY",
						"MASBARANON",
						"POBLACION",
						"POTINGBATO",
						"RIZAL",
						"SAN ROQUE",
						"SANTIAGO",
						"SOROSIMBAJAN",
						"TAWAD",
						"TUNGA",
						"VILLA"
					]
				},
				"MANDAON": {
					"barangay_list": [
						"ALAS",
						"AYAT",
						"BAT-ONGAN",
						"BUGTONG",
						"BURI",
						"CABITAN",
						"CAGMASOSO",
						"CANOMOY",
						"CENTRO",
						"DAYAO",
						"GUINCAIPTAN",
						"LAGUINBANWA",
						"LANTANGAN",
						"LOOC",
						"MABATOBATO",
						"MAOLINGON",
						"NAILABAN",
						"NANIPSAN",
						"PINAMANGCAAN",
						"POBLACION",
						"POLO DACU",
						"SAN JUAN",
						"SAN PABLO",
						"SANTA FE",
						"TAGPU",
						"TUMALAYTAY"
					]
				},
				"MASBATE CITY": {
					"barangay_list": [
						"ANAS",
						"ASID",
						"B. TITONG",
						"BAGUMBAYAN",
						"BANTIGUE",
						"BAPOR (POB.)",
						"BATUHAN",
						"BAYOMBON",
						"BIYONG",
						"BOLO",
						"CAGAY",
						"CAWAYAN EXTERIOR",
						"CAWAYAN INTERIOR",
						"CENTRO (POB.)",
						"ESPINOSA",
						"F. MAGALLANES",
						"IBINGAY",
						"IGANG",
						"KALIPAY (POB.)",
						"KINAMALIGAN",
						"MALINTA",
						"MAPIÑA",
						"MAYNGARAN",
						"NURSERY",
						"PATING (POB.)",
						"PAWA",
						"SINALONGAN",
						"TUGBO",
						"UBONGAN DACU",
						"USAB"
					]
				},
				"MILAGROS": {
					"barangay_list": [
						"BACOLOD",
						"BANGAD",
						"BARA",
						"BONBON",
						"CALASUCHE",
						"CALUMPANG (TAISAN)",
						"CAPACULAN",
						"CAYABON",
						"GUINLUTHANGAN",
						"JAMORAWON",
						"MAGSALANGI",
						"MATAGBAC",
						"MATANGLAD",
						"MATIPORON",
						"MOISES R. ESPINOSA",
						"NARANGASAN",
						"PAMANGPANGON",
						"PARAISO (POTOT)",
						"POBLACION EAST",
						"POBLACION WEST",
						"SAN ANTONIO",
						"SAN CARLOS",
						"SAWMILL",
						"TAGBON",
						"TAWAD",
						"TIGBAO",
						"TINACLIPAN (BATO)"
					]
				},
				"MOBO": {
					"barangay_list": [
						"BAANG",
						"BAGACAY",
						"BALATUCAN",
						"BARAG",
						"DACU",
						"FABRICA",
						"GUINTORELAN",
						"HOLJOGON",
						"LALAGUNA",
						"LOMOCLOC",
						"LUYONG CATUNGAN",
						"MABUHAY",
						"MANDALI",
						"MAPUYO",
						"MARINTOC",
						"NASUNDUAN",
						"PINAMALATICAN",
						"PINAMARBUHAN",
						"POBLACION DIST. I",
						"POBLACION DIST. II",
						"POLOT",
						"SAMBULAWAN",
						"SANTA MARIA",
						"SAWMILL",
						"TABUC",
						"TUGAWE",
						"TUGBO",
						"UMABAY EXTERIOR",
						"UMABAY INTERIOR"
					]
				},
				"MONREAL": {
					"barangay_list": [
						"CANTORNA",
						"FAMOSA",
						"GUINHADAP",
						"MACARTHUR",
						"MAGLAMBONG",
						"MOROCBOROCAN",
						"POBLACION",
						"REAL",
						"RIZAL",
						"SANTO NIÑO",
						"TOGORON"
					]
				},
				"PALANAS": {
					"barangay_list": [
						"ANTIPOLO",
						"BANCO",
						"BIGA-A",
						"BONTOD",
						"BUENASUERTE",
						"INTUSAN",
						"JOSE A. ABENIR SR. (LIBTONG)",
						"MAANAHAO",
						"MABINI",
						"MALATAWAN",
						"MALIBAS",
						"MARAVILLA",
						"MATUGNAO",
						"MIABAS",
						"NABANGIG",
						"NIPA",
						"PARINA",
						"PIÑA",
						"POBLACION",
						"SALVACION",
						"SAN ANTONIO",
						"SAN CARLOS",
						"SAN ISIDRO",
						"SANTA CRUZ"
					]
				},
				"PIO V. CORPUZ (LIMBUHAN)": {
					"barangay_list": [
						"ALEGRIA",
						"BUENASUERTE",
						"BUGANG",
						"BUGTONG",
						"BUNDUCAN",
						"CABANGRAYAN",
						"CALONGONGAN",
						"CASABANGAN",
						"GUINDAWAHAN",
						"LABIGAN",
						"LAMPUYANG",
						"MABUHAY",
						"PALHO",
						"POBLACION",
						"SALVACION",
						"TANQUE",
						"TUBIGAN",
						"TUBOG"
					]
				},
				"PLACER": {
					"barangay_list": [
						"AGUADA",
						"BAN-AO",
						"BURABOD",
						"CABANGCALAN",
						"CALUMPANG",
						"CAMAYABSAN",
						"DAANLUNGSOD",
						"DANGPANAN",
						"DARAGA",
						"GUIN-AWAYAN",
						"GUINHAN-AYAN",
						"KATIPUNAN",
						"LIBAS",
						"LOCSO-AN",
						"LUNA",
						"MAHAYAG",
						"MAHAYAHAY",
						"MANLUT-OD",
						"MATAGANTANG",
						"NABOCTOT",
						"NAGARAO",
						"NAINDAY",
						"NAOCONDIOT",
						"PASIAGON",
						"PILI",
						"POBLACION",
						"PURO",
						"QUIBRADA",
						"SAN MARCOS",
						"SANTA CRUZ",
						"TABOC",
						"TAN-AWAN",
						"TAVERNA",
						"TUBOD",
						"VILLA INOCENCIO"
					]
				},
				"SAN FERNANDO": {
					"barangay_list": [
						"ALTAVISTA",
						"BAYANIHAN POB. (DISTRICT 4)",
						"BAYBAYDAGAT POB. (DISTRICT 1)",
						"BENITINAN",
						"BUENASUERTE",
						"BUENAVISTA",
						"BUENOS AIRES",
						"BUYO",
						"CAÑELAS",
						"CORBADA",
						"DAPLIAN",
						"DEL ROSARIO",
						"IPIL",
						"LAHONG",
						"LUMBIA",
						"MAGKAIPIT",
						"MAGSASAKA POB. (DISTRICT 3)",
						"MINIO",
						"PINAMOGHAAN",
						"PROGRESO",
						"RESURRECCION",
						"SALVACION",
						"SILANGAN POB. (DISTRICT 2)",
						"SOWA",
						"TALISAY",
						"VALPARAISO"
					]
				},
				"SAN JACINTO": {
					"barangay_list": [
						"ALMIÑE",
						"BAGACAY",
						"BAGAHANGLAD",
						"BARTOLABAC",
						"BURGOS",
						"CALIPAT-AN",
						"DANAO",
						"DISTRICT I (POB.)",
						"DISTRICT II (POB.)",
						"DISTRICT III (POB.)",
						"DISTRICT IV (POB.)",
						"DORONG-AN DAPLIAN",
						"INTERIOR",
						"JAGNA-AN",
						"LUNA",
						"MABINI",
						"PIÑA",
						"ROOSEVELT",
						"SAN ISIDRO",
						"SANTA ROSA",
						"WASHINGTON"
					]
				},
				"SAN PASCUAL": {
					"barangay_list": [
						"BOCA CHICA",
						"BOLOD (POB.)",
						"BUSING",
						"CUEVA",
						"DANGCALAN",
						"HALABANGBAYBAY",
						"INIWARAN",
						"KI-BUAYA (RIZAL)",
						"KI-ROMERO (ROXAS)",
						"LAURENTE",
						"MABINI",
						"MABUHAY",
						"MALAKING ILOG",
						"MAPANIQUE",
						"NAZARENO",
						"PINAMASINGAN",
						"QUINTINA",
						"SAN JOSE",
						"SAN PEDRO",
						"SAN RAFAEL",
						"SANTA CRUZ",
						"TERRAPLIN (POB.)"
					]
				},
				"USON": {
					"barangay_list": [
						"ARADO",
						"ARMENIA",
						"AURORA",
						"BADLING",
						"BONIFACIO",
						"BUENASUERTE",
						"BUENAVISTA",
						"CAMPANA",
						"CANDELARIA",
						"CENTRO",
						"CROSSING",
						"DAPDAP",
						"DEL CARMEN",
						"DEL ROSARIO",
						"LIBERTAD",
						"MABINI",
						"MABUHAY",
						"MADAO",
						"MAGSAYSAY",
						"MARCELLA",
						"MIAGA",
						"MONGAHAY",
						"MOROCBOROCAN",
						"PAGUIHAMAN",
						"PANICIJAN",
						"POBLACION",
						"QUEZON",
						"SAN ISIDRO",
						"SAN JOSE",
						"SAN MATEO",
						"SAN RAMON",
						"SAN VICENTE",
						"SANTO CRISTO",
						"SAWANG",
						"SIMAWA"
					]
				}
			}
		},
		"SORSOGON": {
			"municipality_list": {
				"BARCELONA": {
					"barangay_list": [
						"ALEGRIA",
						"BAGACAY",
						"BANGATE",
						"BUGTONG",
						"CAGANG",
						"FABRICA",
						"JIBONG",
						"LAGO",
						"LAYOG",
						"LUNETA",
						"MACABARI",
						"MAPAPAC",
						"OLANDIA",
						"PAGHALUBAN",
						"POBLACION CENTRAL",
						"POBLACION NORTE",
						"POBLACION SUR",
						"PUTIAO",
						"SAN ANTONIO",
						"SAN ISIDRO",
						"SAN RAMON",
						"SAN VICENTE",
						"SANTA CRUZ",
						"SANTA LOURDES",
						"TAGDON"
					]
				},
				"BULAN": {
					"barangay_list": [
						"A. BONIFACIO",
						"ABAD SANTOS",
						"AGUINALDO",
						"ANTIPOLO",
						"BEGUIN",
						"BENIGNO S. AQUINO (IMELDA)",
						"BICAL",
						"BONGA",
						"BUTAG",
						"CADANDANAN",
						"CALOMAGON",
						"CALPI",
						"COCOK-CABITAN",
						"DAGANAS",
						"DANAO",
						"DOLOS",
						"E. QUIRINO",
						"FABRICA",
						"G. DEL PILAR (TANGA)",
						"GATE",
						"INARARAN",
						"J. GERONA",
						"J.P. LAUREL (PON-OD)",
						"JAMORAWON",
						"LAJONG",
						"LIBERTAD",
						"M. ROXAS",
						"MAGSAYSAY",
						"MANAGANAGA",
						"MARINAB",
						"MONTECALVARIO",
						"N. ROQUE (RIZAL)",
						"NAMO",
						"NASUJE",
						"OBRERO",
						"OSMEÑA",
						"OTAVI",
						"PADRE DIAZ",
						"PALALE",
						"QUEZON",
						"R. GERONA",
						"RECTO",
						"SAGRADA",
						"SAN FRANCISCO",
						"SAN ISIDRO",
						"SAN JUAN BAG-O",
						"SAN JUAN DAAN",
						"SAN RAFAEL",
						"SAN RAMON",
						"SAN VICENTE",
						"SANTA REMEDIOS",
						"SANTA TERESITA",
						"SIGAD",
						"SOMAGONGSONG",
						"TAROMATA",
						"ZONE I POB. (BGY. 1- SOUTH ILAWOD)",
						"ZONE II POB. (BGY. 2- WEST ILAWOD)",
						"ZONE III POB. (BGY. 3- EAST ILAWOD)",
						"ZONE IV POB. (BGY. 4- WEST CENTRAL)",
						"ZONE V POB. (BGY. 5-LANIPAN)",
						"ZONE VI POB. (BGY. 6- BAYBAY)",
						"ZONE VII POB. (BGY. 7- IRAYA)",
						"ZONE VIII POB. (BGY. 8- LOYO)"
					]
				},
				"BULUSAN": {
					"barangay_list": [
						"BAGACAY",
						"CENTRAL (POB.)",
						"COGON",
						"DANCALAN",
						"DAPDAP (POB.)",
						"LALUD",
						"LOOBAN (POB.)",
						"MABUHAY (POB.)",
						"MADLAWON (POB.)",
						"POCTOL (POB.)",
						"POROG",
						"SABANG (POB.)",
						"SALVACION",
						"SAN ANTONIO",
						"SAN BERNARDO",
						"SAN FRANCISCO",
						"SAN ISIDRO",
						"SAN JOSE",
						"SAN RAFAEL",
						"SAN ROQUE",
						"SAN VICENTE (BUHANG)",
						"SANTA BARBARA",
						"SAPNGAN (POB.)",
						"TINAMPO"
					]
				},
				"CASIGURAN": {
					"barangay_list": [
						"ADOVIS (POB.)",
						"BOTON",
						"BURGOS",
						"CASAY",
						"CAWIT",
						"CENTRAL (POB.)",
						"COGON",
						"COLAMBIS",
						"ESCUALA",
						"INLAGADIAN",
						"LUNGIB",
						"MABINI",
						"PONONG",
						"RIZAL",
						"SAN ANTONIO (BOHO)",
						"SAN ISIDRO",
						"SAN JUAN",
						"SAN PASCUAL",
						"SANTA CRUZ",
						"SOMAL-OT (POB.)",
						"TIGBAO",
						"TIMBAYOG (POB.)",
						"TIRIS",
						"TRECE MARTIREZ",
						"TULAY"
					]
				},
				"CASTILLA": {
					"barangay_list": [
						"AMOMONTING",
						"BAGALAYAG",
						"BAGONG SIRANG",
						"BONGA",
						"BUENAVISTA",
						"BURABOD",
						"CABURACAN",
						"CANJELA",
						"COGON",
						"CUMADCAD",
						"DANGCALAN",
						"DINAPA",
						"LA UNION",
						"LIBTONG",
						"LORETO",
						"MACALAYA",
						"MARACABAC",
						"MAYON",
						"MAYPANGI",
						"MILAGROSA",
						"MILUYA",
						"MONTE CARMELO",
						"ORAS",
						"PANDAN",
						"POBLACION",
						"QUIRAPI",
						"SACLAYAN",
						"SALVACION",
						"SAN ISIDRO",
						"SAN RAFAEL",
						"SAN ROQUE",
						"SAN VICENTE",
						"SOGOY",
						"TOMALAYTAY"
					]
				},
				"DONSOL": {
					"barangay_list": [
						"ALIN",
						"AWAI",
						"BANBAN",
						"BANDI",
						"BANUANG GURANG",
						"BARAS",
						"BAYAWAS",
						"BORORAN BARANGAY 1 (POB.)",
						"CABUGAO",
						"CENTRAL BARANGAY 2 (POB.)",
						"CRISTO",
						"DANCALAN",
						"DE VERA",
						"GIMAGAAN",
						"GIRAWAN",
						"GOGON",
						"GURA",
						"JUAN ADRE",
						"LOURDES",
						"MABINI",
						"MALAPOC",
						"MALINAO",
						"MARKET SITE BARANGAY 3 (POB.)",
						"NEW MAGUISA",
						"OGOD (CROSSING)",
						"OLD MAGUISA",
						"ORANGE",
						"PANGPANG",
						"PARINA",
						"PAWALA",
						"PINAMANAAN",
						"POSO POB. (BARANGAY 5)",
						"PUNTA WALING-WALING POB. (BARANGAY 4)",
						"RAWIS",
						"SAN ANTONIO",
						"SAN ISIDRO",
						"SAN JOSE",
						"SAN RAFAEL",
						"SAN RAMON",
						"SAN VICENTE",
						"SANTA CRUZ",
						"SEVILLA",
						"SIBAGO",
						"SUGUIAN",
						"TAGBAC",
						"TINANOGAN",
						"TONGDOL",
						"TRES MARIAS",
						"TUBA",
						"TUPAS",
						"VINISITAHAN"
					]
				},
				"GUBAT": {
					"barangay_list": [
						"ARIMAN",
						"BAGACAY",
						"BALUD DEL NORTE (POB.)",
						"BALUD DEL SUR (POB.)",
						"BENGUET",
						"BENTUCO",
						"BERIRAN",
						"BUENAVISTA",
						"BULACAO",
						"CABIGAAN",
						"CABIGUHAN",
						"CARRIEDO",
						"CASILI",
						"COGON",
						"COTA NA DACO (POB.)",
						"DITA",
						"JUPI",
						"LAPINIG",
						"LUNA-CANDOL (POB.)",
						"MANAPAO",
						"MANOOK (POB.)",
						"NAAGTAN",
						"NATO",
						"NAZARENO",
						"OGAO",
						"PACO",
						"PANGANIBAN (POB.)",
						"PARADIJON (POB.)",
						"PATAG",
						"PAYAWIN",
						"PINONTINGAN (POB.)",
						"RIZAL",
						"SAN IGNACIO",
						"SANGAT",
						"SANTA ANA",
						"TABI",
						"TAGAYTAY",
						"TIGKIW",
						"TIRIS",
						"TOGAWE",
						"UNION",
						"VILLAREAL"
					]
				},
				"IROSIN": {
					"barangay_list": [
						"BACOLOD (POB.)",
						"BAGSANGAN",
						"BATANG",
						"BOLOS",
						"BUENAVISTA",
						"BULAWAN",
						"CARRIEDO",
						"CASINI",
						"CAWAYAN",
						"COGON",
						"GABAO",
						"GULANG-GULANG",
						"GUMAPIA",
						"LIANG",
						"MACAWAYAN",
						"MAPASO",
						"MONBON",
						"PATAG",
						"SALVACION",
						"SAN AGUSTIN (POB.)",
						"SAN ISIDRO",
						"SAN JUAN (POB.)",
						"SAN JULIAN (POB.)",
						"SAN PEDRO",
						"SANTO DOMINGO (LAMBOON)",
						"TABON-TABON",
						"TINAMPO",
						"TONGDOL"
					]
				},
				"JUBAN": {
					"barangay_list": [
						"ANOG",
						"AROROY",
						"BACOLOD",
						"BINANUAHAN",
						"BIRIRAN",
						"BURABURAN",
						"CALATEO",
						"CALMAYON",
						"CAROHAYON",
						"CATANAGAN",
						"CATANUSAN",
						"COGON",
						"EMBARCADERO",
						"GURUYAN",
						"LAJONG",
						"MAALO",
						"NORTH POBLACION",
						"PUTING SAPA",
						"RANGAS",
						"SABLAYAN",
						"SIPAYA",
						"SOUTH POBLACION",
						"TABOC",
						"TINAGO",
						"TUGHAN"
					]
				},
				"MAGALLANES": {
					"barangay_list": [
						"AGUADA NORTE",
						"AGUADA SUR",
						"ANIBONG",
						"BACALON",
						"BACOLOD",
						"BANACUD",
						"BEHIA",
						"BIGA",
						"BINISITAHAN DEL NORTE",
						"BINISITAHAN DEL SUR",
						"BITON",
						"BULALA",
						"BUSAY",
						"CADITAAN",
						"CAGBOLO",
						"CAGTALABA",
						"CAWIT EXTENSION",
						"CAWIT PROPER",
						"GINANGRA",
						"HUBO",
						"INCARIZAN",
						"LAPINIG",
						"MAGSAYSAY",
						"MALBOG",
						"PANTALAN",
						"PAWIK",
						"PILI",
						"POBLACION",
						"SALVACION",
						"SANTA ELENA",
						"SIUTON",
						"TAGAS",
						"TULATULA NORTE",
						"TULATULA SUR"
					]
				},
				"MATNOG": {
					"barangay_list": [
						"BALOCAWE",
						"BANOGAO",
						"BANUANGDAAN",
						"BARIIS",
						"BOLO",
						"BON-OT BIG",
						"BON-OT SMALL",
						"CABAGAHAN",
						"CALAYUAN",
						"CALINTAAN",
						"CALOOCAN (POB.)",
						"CALPI",
						"CAMACHILES (POB.)",
						"CAMCAMAN (POB.)",
						"CORON-CORON",
						"CULASI",
						"GADGARON",
						"GENABLAN OCCIDENTAL",
						"GENABLAN ORIENTAL",
						"HIDHID",
						"LABOY",
						"LAJONG",
						"MAMBAJOG",
						"MANJUNLAD",
						"MANURABI",
						"NABURACAN",
						"PAGHULIRAN",
						"PANGI",
						"PAWA",
						"POROPANDAN",
						"SANTA ISABEL",
						"SINALMACAN",
						"SINANG-ATAN",
						"SINIBARAN",
						"SISIGON",
						"SUA",
						"SULANGAN",
						"TABLAC (POB.)",
						"TABUNAN (POB.)",
						"TUGAS"
					]
				},
				"PILAR": {
					"barangay_list": [
						"ABAS",
						"ABUCAY",
						"BANTAYAN",
						"BANUYO (POB.)",
						"BAYASONG",
						"BAYAWAS",
						"BINANUAHAN (POB.)",
						"CABIGUAN",
						"CAGDONGON",
						"CALONGAY",
						"CALPI",
						"CATAMLANGAN",
						"COMAPO-CAPO",
						"DANLOG",
						"DAO (POB.)",
						"DAPDAP",
						"DEL ROSARIO (BUAL)",
						"ESMERADA",
						"ESPERANZA",
						"GINABLAN",
						"GUIRON",
						"INANG",
						"INAPUGAN",
						"LEONA",
						"LIPASON",
						"LOURDES",
						"LUBIANO",
						"LUMBANG",
						"LUNGIB",
						"MABANATE",
						"MALBOG",
						"MARIFOSQUE (POB.)",
						"MERCEDES",
						"MIGABOD",
						"NASPI",
						"PALANAS",
						"PANGPANG",
						"PINAGSALOG",
						"PINEDA",
						"POCTOL",
						"PUDO",
						"PUTIAO",
						"SACNANGAN",
						"SALVACION",
						"SAN ANTONIO (MILLABAS)",
						"SAN ANTONIO (SAPA)",
						"SAN JOSE",
						"SAN RAFAEL",
						"SANTA FE"
					]
				},
				"PRIETO DIAZ": {
					"barangay_list": [
						"BRILLANTE (POB.)",
						"BULAWAN",
						"CALAO",
						"CARAYAT",
						"DIAMANTE",
						"GOGON",
						"LUPI",
						"MANINGCAY DE ORO",
						"MANLABONG",
						"PERLAS",
						"QUIDOLOG",
						"RIZAL",
						"SAN ANTONIO",
						"SAN FERNANDO",
						"SAN ISIDRO",
						"SAN JUAN",
						"SAN RAFAEL",
						"SAN RAMON",
						"SANTA LOURDES",
						"SANTO DOMINGO",
						"TALISAYAN",
						"TUPAZ",
						"ULAG"
					]
				},
				"SANTA MAGDALENA": {
					"barangay_list": [
						"BARANGAY POBLACION I",
						"BARANGAY POBLACION II",
						"BARANGAY POBLACION III",
						"BARANGAY POBLACION IV",
						"LA ESPERANZA",
						"PEÑAFRANCIA",
						"SALVACION",
						"SAN ANTONIO",
						"SAN BARTOLOME (TALAONGAN)",
						"SAN EUGENIO",
						"SAN ISIDRO",
						"SAN RAFAEL",
						"SAN ROQUE",
						"SAN SEBASTIAN"
					]
				},
				"SORSOGON CITY": {
					"barangay_list": [
						"ABUYOG",
						"ALMENDRAS-COGON (POB.)",
						"BALETE",
						"BALOGO",
						"BALOGO ( FR. THE MUN. OF BACON)",
						"BARAYONG",
						"BASUD",
						"BATO",
						"BIBINCAHAN",
						"BITAN-O/DALIPAY (POB.)",
						"BOGÑA",
						"BON-OT",
						"BUCALBUCALAN",
						"BUENAVISTA",
						"BUENAVISTA ( FR. THE MUN. OF BACON)",
						"BUHATAN",
						"BULABOG",
						"BURABOD (POB.)",
						"CABARBUHAN",
						"CABID-AN",
						"CAMBULAGA",
						"CAPUY",
						"CARICARAN",
						"DEL ROSARIO",
						"GATBO",
						"GIMALOTO",
						"GUINLAJON",
						"JAMISLAGAN",
						"MACABOG",
						"MARICRUM",
						"MARINAS",
						"OSIAO",
						"PAMURAYAN",
						"PANGPANG",
						"PANLAYAAN",
						"PEÑAFRANCIA",
						"PIOT (POB.)",
						"POBLACION",
						"POLVORISTA (POB.)",
						"RAWIS",
						"RIZAL",
						"SALOG (POB.)",
						"SALVACION",
						"SALVACION ( FR. THE MUN. OF BACON)",
						"SAMPALOC (POB.)",
						"SAN ISIDRO",
						"SAN ISIDRO ( FR. THE MUN. OF BACON)",
						"SAN JUAN ( FR. THE MUN. OF BACON)",
						"SAN JUAN (RORO)",
						"SAN PASCUAL",
						"SAN RAMON",
						"SAN ROQUE",
						"SAN VICENTE",
						"SANTA CRUZ",
						"SANTA LUCIA",
						"SANTO DOMINGO",
						"SANTO NIÑO",
						"SAWANGA",
						"SIRANGAN (POB.)",
						"SUGOD",
						"SULUCAN (POB.)",
						"TALISAY (POB.)",
						"TICOL",
						"TUGOS"
					]
				}
			}
		}
	}
}
